Workbook

Sheet Page de garde
B2: CBRE | EMEA | QHSE | Formulaire | RASSa - Evaluation des risques
B3: Evaluation des risques
B5: Nom du compte : | D5: CBRE GWS France SAS
B7: Adresse du site concerné : | D7: 17 quai du Président Paul Doumer - 92400 COURBEVOIE
B9: Périmètre évalué : | D9: Maintenance multitechnique du bâtiment - coordination des entreprises sous-traitantes - Facility management - gestion de projet d'aménagement
B11: Unités de Travail (UT) : Groupement de personnes susceptibles d'être exposées au risque | H11: Cocher les unités de travail évalués
B12: UT 1 : | C12: Equipe administrative (Contract Support, RH, achat, finance, commerce) | H12: x
B13: UT 2 : | C13: Direction générale et opérationnelle (Directeur Général, Directeur Opérationnel, AGM, Responsable Multi-site) | H13: x
B14: UT 3 : | C14: Responsables de site et coordinateurs soft - Contrats à dominante soft | H14: x
B15: UT 4 : | C15: Responsables de site et coordinateurs techniques - Contrats à dominante technique | H15: x
B16: UT 5 : | C16: Techniciens multitechniques | H16: x
B17: UT 6 : | C17: Techniciens frigoristes | H17: x
B18: UT 7 : | C18: Equipiers multi-services (Factotums, Handymans) | H18: x
B19: UT 8 : | C19: Direction Projet / Technique et QHSE | H19: x
B20: UT 9 : | C20: Sous-traitant | H20: x
B22: Version | C22: Objet (contenu de la mise à jour) | E22: Nom de(s) l'évaluateur(s) | G22: Date de mise à jour | H22: Validation Manager
B23: V1 | C23: Mise à jour du Document Unique d'Evaluation des Risques Professionnels | E23: Nicolas Bernard / Islem Resgui / Theo Rocca | G23: 45945
B24: V2 | C24: Présentation, mise à jour,validation | E24: Membres du CSSCT | G24: 46055

Sheet Risk Register
B1: CBRE | EMEA | QHSE | Formulaire | RASSa - Evaluation des risques
B2: Document Unique d'Evaluation des Risques Professionnels
B4: ='Page de garde'!D5 -> CBRE GWS France SAS | M4: Périmètre : | O4: ='Page de garde'!D9 -> Maintenance multitechnique du bâtiment - coordination des entreprises sous-traitantes - Facility management - gestion de projet d'aménagement | AH4: Date de mise à jour : | AI4: ='Page de garde'!G23 -> 45945
B6: ='Page de garde'!D7 -> 17 quai du Président Paul Doumer - 92400 COURBEVOIE | AH6: Par : | AI6: ='Page de garde'!E23 -> Nicolas Bernard / Islem Resgui / Theo Rocca
W7: Mesures de prévention applicables
B8: 1. Sélectionner les principales opérations ou tâches effectuées sur site | C8: 2. Déterminer les tâches exécutées sur site | D8: 3. unités de travail concernées | M8: 4a. Quels sont les principaux risques de cette tâche ? | N8: 4b. Risque INRS | O8: 5. Quels sont les équipements concernés ? | P8: 6. Fonctionnement normal ou dégradé ? | Q8: 7. A quelle fréquence faites vous cette tâche ? | R8: 8. Probabilité qu'un accident survienne | T8: 9. Gravité potentielle | V8: Risque Brute | W8: 10. Spécifier si des éléments de sécurité sont constitutifs de l'équipement | X8: 11. Y a-t-il une règle qui sauvent CBRE qui s'applique à cette tâche ? | Y8: 12. Quels sont les EPC et/ou EPI nécessaire pour effectuer cette tâche ? | Z8: En place ? | AA8: 13. Faut-il avoir suivi des formations/habilitations pour exécuter cette tâche ? | AB8: En place ? | AC8: 14. Y at-il des procédures / protocole à suivre ? Lesquels ? | AD8: En place? | AE8: Risque résiduel - le facteur humain | AG8: Risque net | AH8: 15. Des actions complémentaires sont-elles à prévoir ? Lesquelles ? | AI8: 16. Autre chose ?
B9: Principales opérations / tâches | C9: Facteur d'exposition | D9: UT 1 (adm) | E9: UT2 (DIR / AGM) | F9: UT3 (Coord Soft) | G9: UT4 (Coord Tech) | H9: UT5 (TECH) | I9: UT6 (Frigo) | J9: UT7 (Handyan) | K9: UT8 (PJM / DT QHSE) | L9: UT9 (SST) | M9: Risques | O9: Equipement | P9: Fonctionnement | Q9: Fréquence d'exposition | R9: Probabilité | S9: Score H+I | T9: Gravité | U9: Score 1 | V9: Risk Before Mitigation | W9: Mesures de conception | X9: Règles qui sauvent | Y9: Equipement de protection collectif et individuel | AA9: Formation spécifique | AC9: Mesures organisationnelles | AE9: Alea | AF9: Score 2 | AG9: Risk After Mitigation | AH9: Further risk treatments, controls, mitigation action | AI9: Comment
B10: Travaux électriques | C10: Relamping | H10: x | J10: x | M10: Electrisation / électrocution | N10: 14. Risques liés à l'électricité | O10: Luminaire | P10: dégradé | Q10: 2 | R10: 2 | S10: =Q10+R10 -> 4 | T10: 4 | U10: =VLOOKUP($T10,Cotation!$G$6:$H$10,2,(FALSE)) -> 3 | V10: =HLOOKUP($S10,Cotation!$I$5:$M$10,'Risk Register'!U10,(TRUE)) -> S | W10: Mesure de conception des installations électriques selon norme NFC 15100 | X10: Règle 1 - Autorisation de Travail ( compétence) Regle 2 - Consignation Règle 3 - travaux électrique | Y10: Vêtement de travail ( si possilbe Atex / Arc Flash) Chaussures de sécurité Gants de manipulation fine Kit de consignation VAT Balisage de la zone si travail en hauteur | Z10: 0.25 | AA10: Habilitation électrique niveau BS à minima | AB10: 0.25 | AC10: Consignation des énergies préalable au niveau du disjoncteur Loto - condamnation du départ éléctrique Permis de travail électrique EA : Verification de compétence electrique | AD10: 0.25 | AE10: =100%-(Z10+AB10+AD10) -> 0.25 | AF10: =S10*AE10 -> 1 | AG10: =HLOOKUP($AF10,Cotation!$I$5:$M$10,'Risk Register'!U10,(TRUE)) -> M
B11: Travaux électriques | C11: Réarmement de disjoncteur | G11: x | H11: x | J11: x | M11: Electrisation / électrocution | N11: 14. Risques liés à l'électricité | O11: Armoire électrique | P11: dégradé | Q11: 3 | R11: 1 | S11: =Q11+R11 -> 4 | T11: 4 | U11: =VLOOKUP($T11,Cotation!$G$6:$H$10,2,(FALSE)) -> 3 | V11: =HLOOKUP($S11,Cotation!$I$5:$M$10,'Risk Register'!U11,(TRUE)) -> S | W11: Mesure de conception des installations électriques selon norme NFC 15100 | X11: Règle 1 - Autorisation de Travail ( compétence) | Y11: Vêtement de travail Chaussures de sécurité Gants Casque électricien | Z11: 0.25 | AA11: minimum l'habilitation BE Manœuvre ou l'habilitation BS | AB11: 0.25 | AC11: EA : Verification de compétence electriq | AD11: 0.25 | AE11: =100%-(Z11+AB11+AD11) -> 0.25 | AF11: =S11*AE11 -> 1 | AG11: =HLOOKUP($AF11,Cotation!$I$5:$M$10,'Risk Register'!U11,(TRUE)) -> M
B12: Conduite de véhicule | C12: Circulation en voiture / camionnette | D12: x | E12: x | F12: x | G12: x | H12: x | I12: x | J12: x | K12: x | L12: x | M12: Accident de la route | N12: Risques routiers en mission | O12: VL | P12: Normal | Q12: 5 | R12: 4 | S12: =Q12+R12 -> 9 | T12: 5 | U12: =VLOOKUP($T12,Cotation!$G$6:$H$10,2,(FALSE)) -> 2 | V12: =HLOOKUP($S12,Cotation!$I$5:$M$10,'Risk Register'!U12,(TRUE)) -> C | W12: Sécurité intrinsinque des VL | X12: Règle 4 - Conduite | Y12: Sécurité des véhicules (ceinture de sécurité) | Z12: 0.25 | AA12: Formation aux risques routiers | AB12: 0 | AC12: Code de la route applicable à tous Charte de conduite de vehicule CBRE Maintenance des véhicules CBRE - Contrat de "full maintenance" intégré - Contrat intégrant pneumatiques été/hiver | AD12: 0.25 | AE12: =100%-(Z12+AB12+AD12) -> 0.5 | AF12: =S12*AE12 -> 4.5 | AG12: =HLOOKUP($AF12,Cotation!$I$5:$M$10,'Risk Register'!U17,(TRUE)) -> S | AH12: Procédure de vérification (checklist) des véhicules à réaliser par les managers à remettreen place | AI12: Politique de déplacements - Limiter les déplacements et favoriser les visio conférence - Favoriser les déplacements par les transports en commun (train)
B13: Travaux administratifs | C13: Travail sur écran | D13: x | E13: x | F13: x | G13: x | H13: x | I13: x | J13: x | K13: x | L13: x | M13: Fatigue visuelle / TMS | N13: 18. Risques liés au travail sur écran | O13: Ordinateur / écran / caliver et souris | P13: Normal | Q13: 5 | R13: 2 | S13: =Q13+R13 -> 7 | T13: 2 | U13: =VLOOKUP($T13,Cotation!$G$6:$H$10,2,(FALSE)) -> 5 | V13: =HLOOKUP($S13,Cotation!$I$5:$M$10,'Risk Register'!U13,(TRUE)) -> M | W13: Ergonomie des bureaux et chaise ergonomique | X13: non | Y13: Matériel bureautique ergonomique | Z13: 0.25 | AA13: Atelier d'ergonomie Core Safety Training : elearning | AB13: 0.1 | AC13: Non | AD13: 0 | AE13: =100%-(Z13+AB13+AD13) -> 0.65 | AF13: =S13*AE13 -> 4.55 | AG13: =HLOOKUP($AF13,Cotation!$I$5:$M$10,'Risk Register'!U14,(TRUE)) -> M
B14: Manutention manuelle | C14: Ouverture de trappes et regards | H14: x | I14: x | J14: x | M14: Coupure / ecrasement / TMS | N14: 05. Risques liés à la manutention manuelle de charge | O14: Trappes et regards | P14: Normal | Q14: 1 | R14: 2 | S14: =Q14+R14 -> 3 | T14: 3 | U14: =VLOOKUP($T14,Cotation!$G$6:$H$10,2,(FALSE)) -> 4 | V14: =HLOOKUP($S14,Cotation!$I$5:$M$10,'Risk Register'!U14,(TRUE)) -> M | W14: Conception des trappes variable selon age matériaux et utilité | X14: non | Y14: Gants de manutention lourde Chaussure de sécurité Outils de levage Balisage de la zone de travail. | Z14: 0.1 | AA14: Core Safety Training : elearning | AB14: 0 | AC14: Analyse de risque dynmaique ou RAD Check list manutention manuelle MANHa Préférez l'utilisation d'outil de levage spécifique (lève plaque, pioche…) Ne jamais laisser une plaque ouverte sans balisage | AD14: 0 | AE14: =100%-(Z14+AB14+AD14) -> 0.9 | AF14: =S14*AE14 -> 2.7 | AG14: =HLOOKUP($AF14,Cotation!$I$5:$M$10,'Risk Register'!U20,(TRUE)) -> M
B15: Manutention manuelle | C15: Déménagement de meubles | H15: x | I15: x | J15: x | M15: TMS / heurt / choc / ecrasement | N15: 05. Risques liés à la manutention manuelle de charge | O15: Mobilier | P15: Normal | Q15: 5 | R15: 4 | S15: =Q15+R15 -> 9 | T15: 3 | U15: =VLOOKUP($T15,Cotation!$G$6:$H$10,2,(FALSE)) -> 4 | V15: =HLOOKUP($S15,Cotation!$I$5:$M$10,'Risk Register'!U13,(TRUE)) -> S | W15: non | X15: non | Y15: Gants de manutention Chaussure de sécurité | Z15: 0.25 | AA15: Formation gestes et postures Core Safety Training : elearning | AB15: 0.25 | AC15: Analyse de risque dynmaique ou RAD Check list manutention manuelle MANHa Travail à deux pour le mobilier volumineux Utilitation des moyens mécaniques de manutention (chariots, transpalettes, véhicules…) Outils spécifique de levage hors equpement necessitant formation spécifique (CACES) | AD15: 0.25 | AE15: =100%-(Z15+AB15+AD15) -> 0.25 | AF15: =S15*AE15 -> 2.25 | AG15: =HLOOKUP($AF15,Cotation!$I$5:$M$10,'Risk Register'!U13,(TRUE)) -> F
B16: Utilisation d'outils électroportatif | C16: Meulage | G16: x | M16: Coupure / incendie / projection de matière | N16: 13. Risques d'incendie, d'explosion | O16: Meuleuse / disqueuse | P16: Normal | Q16: 2 | R16: 2 | S16: =Q16+R16 -> 4 | T16: 2 | V16: =HLOOKUP($S16,Cotation!$I$5:$M$10,'Risk Register'!U18,(TRUE)) -> F | W16: Outils munis de capot / carter deprotection sur autour de la lame et d'une poignée | X16: Règle 1 - Autorisation de Travail ( compétence) Regle 7 - travail par point chaud | Y16: Gants anticoupure Ecran facial Vêtements de travail balisage de la zone de travail extincteur | AA16: Core safety training : elearning Formation PTW : Travauxparpoint chaud Formation extincteur | AC16: Permis de travail signé Procedure hot work Procedure PTW : Permis Feu Vérification préalable du matériel (verification avant utilisation / inspection annuelle) Choix préalable du disque le plus adaptée au matériau découpé Interdiction d'enlever la poignée | AD16: 0.25 | AE16: =100%-(Z16+AB16+AD16) -> 0.75 | AF16: =S16*AE16 -> 3 | AG16: =HLOOKUP($AF16,Cotation!$I$5:$M$10,'Risk Register'!U18,(TRUE)) -> F
B17: Utilisation d'outils électroportatif | C17: Meulage | H17: x | I17: x | J17: x | M17: Coupure / incendie / projection de matière | N17: 13. Risques d'incendie, d'explosion | O17: Meuleuse / disqueuse | P17: Normal | Q17: 2 | R17: 2 | S17: =Q17+R17 -> 4 | T17: 4 | U17: =VLOOKUP($T17,Cotation!$G$6:$H$10,2,(FALSE)) -> 3 | V17: =HLOOKUP($S17,Cotation!$I$5:$M$10,'Risk Register'!U19,(TRUE)) -> M | W17: Outils munis de capot / carter deprotection sur autour de la lame et d'une poignée | X17: Règle 1 - Autorisation de Travail ( compétence) Regle 7 - travail par point chaud | Y17: Gants anticoupure Ecran facial Vêtements de travail balisage de la zone de travail extincteur | Z17: 0.25 | AA17: Core safety training : elearning | AB17: 0 | AC17: Permis de travail signé Procedure hot work Procedure PTW : Permis Feu Vérification préalable du matériel (verification avant utilisation / inspection annuelle) Choix préalable du disque le plus adaptée au matériau découpé Interdiction d'enlever la poignée | AD17: 0.25 | AE17: =100%-(Z17+AB17+AD17) -> 0.5 | AF17: =S17*AE17 -> 2 | AG17: =HLOOKUP($AF17,Cotation!$I$5:$M$10,'Risk Register'!U19,(TRUE)) -> M
B18: Travaux en hauteur | C18: Travail sur escabeau | G18: x | M18: Chute de hauteur Basculement de l'escabeau Chute d'objet | N18: 02. Risques de chutes de hauteur | O18: Escabeau | P18: Normal | Q18: 3 | R18: 2 | S18: =Q18+R18 -> 5 | T18: 1 | U18: =VLOOKUP($T18,Cotation!$G$6:$H$10,2,(FALSE)) -> 6 | V18: =HLOOKUP($S18,Cotation!$I$5:$M$10,'Risk Register'!U22,(TRUE)) -> S | W18: Escabeau conforme EN 131 (pas de défault structurel, présence des patins anti-dérapant) | X18: Règle 1 - Autorisation de Travail ( compétence) Regle 5 - Travail en hauteur | Y18: Casquette coquée Chaussure de sécurité Gants Lunettes de sécurité Balisage de la zone | Z18: 0.25 | AA18: Core safety training : elearning Formation PTW : Travaux en hauteur au dessus de 1,8 m | AB18: 0 | AC18: Analyse de risque avant travaux ou RAD Inspection escabeau aavnt utilisation Inspection mensuelle WAHSa Privilégier l'utilisation d'une pirl lorsque c'est possible. Vérification de l'équipement avant utilisation (état de conservation, présence de l'ensemble des pièces, stabilité) Matériel ressencé et référencé Permis de travail en hauteur pour les hauteurs de plus de 1,80 signé EA : verification des compétences | AD18: 0.1 | AE18: =100%-(Z18+AB18+AD18) -> 0.65 | AF18: =S18*AE18 -> 3.25 | AG18: =HLOOKUP($AF18,Cotation!$I$5:$M$10,'Risk Register'!U22,(TRUE)) -> M
B19: Travaux en hauteur | C19: Travail sur escabeau | H19: x | I19: x | J19: x | M19: Chute de hauteur Basculement de l'escabeau Chute d'objet | N19: 02. Risques de chutes de hauteur | O19: Escabeau | P19: Normal | Q19: 3 | R19: 4 | S19: =Q19+R19 -> 7 | T19: 3 | U19: =VLOOKUP($T19,Cotation!$G$6:$H$10,2,(FALSE)) -> 4 | V19: =HLOOKUP($S19,Cotation!$I$5:$M$10,'Risk Register'!U23,(TRUE)) -> S | W19: Escabeau conforme EN 131 (pas de défault structurel, présence des patins anti-dérapant) | X19: Règle 1 - Autorisation de Travail ( compétence) Regle 5 - Travail en hauteur | Y19: Casquette coquée Chaussure de sécurité Gants Lunettes de sécurité Balisage de la zone | Z19: 0.25 | AA19: Core safety training :travail en hauteur | AB19: 0 | AC19: Analyse de risque avant travaux ou RAD Privilégier l'utilisation d'une pirl lorsque c'est possible. Vérification de l'équipement avant utilisation (état de conservation, présence de l'ensemble des pièces, stabilité) Matériel ressencé et référencé Permis de travail en hauteur pour les hauteurs de plus de 1,8m signé EA : verification des compétences | AD19: 0.1 | AE19: =100%-(Z19+AB19+AD19) -> 0.65 | AF19: =S19*AE19 -> 4.55 | AG19: =HLOOKUP($AF19,Cotation!$I$5:$M$10,'Risk Register'!U23,(TRUE)) -> S
B20: Travaux électriques | C20: Remplacement de disjoncteur dans une armoire électrique BT | G20: x | H20: x | I20: x | M20: Electrisation / électrocution | N20: 14. Risques liés à l'électricité | O20: Armoire électrique | P20: dégradé | Q20: 2 | R20: 2 | S20: =Q20+R20 -> 4 | T20: 4 | U20: =VLOOKUP($T20,Cotation!$G$6:$H$10,2,(FALSE)) -> 3 | V20: =HLOOKUP($S20,Cotation!$I$5:$M$10,'Risk Register'!U10,(TRUE)) -> S | W20: Mesure de conception des installations électriques selon norme NFC 15100 | X20: Règle 1 - Autorisation de Travail ( compétence) Regle 2 - Consignation Règle 3 - travaux électrique | Y20: Casque électricien Gants électricien Vêtement de travail (arc flash et Atex si possible) Chaussures de sécurité Tapis isolant Kit de consignation VAT Balisage | Z20: 0.25 | AA20: Tous : Habilitation électrique niveau BR à minima Coordinateur : Formation PTW travaux electrique | AB20: 0.25 | AC20: Analyse de risque dynmaique ou RAD Permis de travail electrique signé Consignation des énergies EA : verification des compétences | AD20: 0.25 | AE20: =100%-(Z20+AB20+AD20) -> 0.25 | AF20: =S20*AE20 -> 1 | AG20: =HLOOKUP($AF20,Cotation!$I$5:$M$10,'Risk Register'!U10,(TRUE)) -> M
B21: Travaux électriques | C21: Maintenance electrique BT | G21: x | H21: x | I21: x | M21: Electrisation / électrocution | N21: 14. Risques liés à l'électricité | O21: Equipement électrique | P21: Normal | Q21: 3 | R21: 1 | S21: =Q21+R21 -> 4 | T21: 4 | U21: =VLOOKUP($T21,Cotation!$G$6:$H$10,2,(FALSE)) -> 3 | V21: =HLOOKUP($S21,Cotation!$I$5:$M$10,'Risk Register'!U21,(TRUE)) -> S | W21: Mesure de conception des installations électriques selon norme NFC 15100 | X21: Règle 1 - Autorisation de Travail ( compétence) Regle 2 - Consignation Règle 3 - travaux électrique | Y21: Casque électricien Gants électricien Vêtement de travail (arc flash et Atex si possible) Chaussures de sécurité Tapis isolant Kit de consignation VAT Balisage | Z21: 0.25 | AA21: Tous : Habilitation électrique niveau BR à minima Coordinateur : Formation PTW travaux electrique | AB21: 0.25 | AC21: Analyse de risque dynmaique ou RAD Permis de travail electrique signé Consignation des énergies EA : verification des compétences | AD21: 0.25 | AE21: =100%-(Z21+AB21+AD21) -> 0.25 | AF21: =S21*AE21 -> 1 | AG21: =HLOOKUP($AF21,Cotation!$I$5:$M$10,'Risk Register'!U11,(TRUE)) -> M
B22: Travaux électriques | C22: Recherche de panne électrique | G22: x | H22: x | I22: x | M22: Electrisation / électrocution | N22: 14. Risques liés à l'électricité | O22: Tout équipement électrique | P22: dégradé | Q22: 4 | R22: 3 | S22: =Q22+R22 -> 7 | T22: 4 | U22: =VLOOKUP($T22,Cotation!$G$6:$H$10,2,(FALSE)) -> 3 | V22: =HLOOKUP($S22,Cotation!$I$5:$M$10,'Risk Register'!U15,(TRUE)) -> S | W22: Mesure de conception des installations électriques selon norme NFC 15100 | X22: Règle 1 - Autorisation de Travail ( compétence) Regle 2 - Consignation Règle 3 - travaux électrique | Y22: Casque électricien Gants électricien Vêtement de travail (arc flash et Atex si possible) Chaussures de sécurité Tapis isolant Kit de consignation VAT Balisage | Z22: 0.25 | AA22: Habilitation électrique niveau BR à minima Coordinateur : Formation PTW travaux electrique | AB22: 0.25 | AC22: Analyse de risque dynmaique ou RAD Permis de travail electrique signé Consignation des énergies EA : verification des compétences | AD22: 0.25 | AE22: =100%-(Z22+AB22+AD22) -> 0.25 | AF22: =S22*AE22 -> 1.75 | AG22: =HLOOKUP($AF22,Cotation!$I$5:$M$10,'Risk Register'!U15,(TRUE)) -> F
B23: Travaux en hauteur | C23: Travail sur nacelle élévatrice | G23: x | H23: x | I23: x | M23: Chute de hauteur Chute d'objet | N23: 02. Risques de chutes de hauteur | O23: Nacelle élévatrice | P23: Normal | Q23: 2 | R23: 1 | S23: =Q23+R23 -> 3 | T23: 4 | U23: =VLOOKUP($T23,Cotation!$G$6:$H$10,2,(FALSE)) -> 3 | V23: =HLOOKUP($S23,Cotation!$I$5:$M$10,'Risk Register'!U22,(TRUE)) -> M | W23: Equipement conforme et CE | X23: Règle 1 - Autorisation de Travail ( compétence) Regle 6 - Travail en hauteur | Y23: Casque avec jugulaire Chaussure de sécurité gants de travail équipement de protection contre les chute de hauteur (harnais et longe sans absorbeur) Balisage de la zone de travail | Z23: 0.25 | AA23: Formation nacelle : - CACES 486 A linéaire - CACES 486 B mouvements horizontaux ou une rotation Formation port du harnais Coordinateur : Formation PTW travail en hauteur | AB23: 0.25 | AC23: Analyse de risque dynmaique ou RAD Permis de travail en hauteur signé EA : verification des compétences | AD23: 0.25 | AE23: =100%-(Z23+AB23+AD23) -> 0.25 | AF23: =S23*AE23 -> 0.75 | AG23: =HLOOKUP($AF23,Cotation!$I$5:$M$10,'Risk Register'!U22,(TRUE)) -> M
B24: Travaux mécaniques | C24: Remplacement de courroies moteur extracteur d'air | G24: x | H24: x | M24: Electrisation / électrocution Coupure / heurt | N24: 14. Risques liés à l'électricité | O24: Extracteur d'air | P24: dégradé | Q24: 1 | R24: 1 | S24: =Q24+R24 -> 2 | T24: 3 | U24: =VLOOKUP($T24,Cotation!$G$6:$H$10,2,(FALSE)) -> 4 | V24: =HLOOKUP($S24,Cotation!$I$5:$M$10,'Risk Register'!U24,(TRUE)) -> M | W24: non | X24: Règle 1 - Autorisation de Travail ( compétence) Regle 2 - Consignation Règle 3 - travaux électrique | Y24: Casque / Chaussure de sécurité / gants de travail / lunettes de sécurité Kit de consignation Balisage de la zone de travail | Z24: 0.25 | AA24: Habiitation BR pour les consignations électriques | AB24: 0.25 | AC24: Analyse de risque dynmaique ou RAD Permis de travail electrique signé Consignation des énergies EA : verification des compétences | AD24: 0.25 | AE24: =100%-(Z24+AB24+AD24) -> 0.25 | AF24: =S24*AE24 -> 0.5 | AG24: =HLOOKUP($AF24,Cotation!$I$5:$M$10,'Risk Register'!U24,(TRUE)) -> F
B25: Travaux mécaniques | C25: Remplacement de filtre CTA | G25: x | H25: x | I25: x | M25: Manutention | N25: 09. Risques liés aux équipements de travail | O25: CTA | P25: dégradé | Q25: 4 | R25: 2 | S25: =Q25+R25 -> 6 | T25: 2 | U25: =VLOOKUP($T25,Cotation!$G$6:$H$10,2,(FALSE)) -> 5 | V25: =HLOOKUP($S25,Cotation!$I$5:$M$10,'Risk Register'!U25,(TRUE)) -> M | W25: Refixer systéatiquement des capôts et boulonneries | X25: Règle 1 - Autorisation de Travail ( compétence) Regle 2 - Consignation | Y25: Casque / Chaussure de sécurité / gants de travail / lunettes de sécurité Kit de consignation Balisage de la zone de travail | Z25: 0.25 | AA25: non | AB25: 0 | AC25: Analyse de risque dynmaique ou RAD Arrêt préalable de la CTA au commutateur avec cadenas Test de redemarage Vérification prélabale des outillages | AD25: 0.25 | AE25: =100%-(Z25+AB25+AD25) -> 0.5 | AF25: =S25*AE25 -> 3 | AG25: =HLOOKUP($AF25,Cotation!$I$5:$M$10,'Risk Register'!U25,(TRUE)) -> F
B26: Travaux électriques | C26: Mesure d'intensité | G26: x | H26: x | I26: x | M26: Electrisation / electrocution | N26: 14. Risques liés à l'électricité | O26: Equipement électrique | P26: Normal | Q26: 3 | R26: 1 | S26: =Q26+R26 -> 4 | T26: 4 | U26: =VLOOKUP($T26,Cotation!$G$6:$H$10,2,(FALSE)) -> 3 | V26: =HLOOKUP($S26,Cotation!$I$5:$M$10,'Risk Register'!U26,(TRUE)) -> S | W26: Mesure de conception des installations électriques selon norme NFC 15100 | X26: Règle 1 - Autorisation de Travail ( compétence) Regle 3 - travaux electriques | Y26: Casque électricien Gants électricien Vêtement de travail ( Atex et Arc Flach si possible) Multimètre | Z26: 0.25 | AA26: Habilitation électrique niveau BR à minima Coordinateur : Formation PTW travaux electrique | AB26: 0.25 | AC26: Permis de travail électrique signé Repérage des plans Etiquetage Suivi des modes opératoires | AD26: 0.25 | AE26: =100%-(Z26+AB26+AD26) -> 0.25 | AF26: =S26*AE26 -> 1 | AG26: =HLOOKUP($AF26,Cotation!$I$5:$M$10,'Risk Register'!U26,(TRUE)) -> M
B27: Relevés et mesures | C27: Relevé de compteur | G27: x | H27: x | I27: x | J27: x | M27: Ecrasement des mains/ pieds | N27: 09. Risques liés aux équipements de travail | O27: Plaque / couvercle de regard | P27: Normal | Q27: 1 | R27: 2 | S27: =Q27+R27 -> 3 | T27: 3 | U27: =VLOOKUP($T27,Cotation!$G$6:$H$10,2,(FALSE)) -> 4 | V27: =HLOOKUP($S27,Cotation!$I$5:$M$10,'Risk Register'!U27,(TRUE)) -> M | W27: non | Y27: Casque / casquette coquéex Chaussures de sécurité gants de manutention Lunette de sécurité Outil de levage de plaque | Z27: 0.25 | AA27: Gestes et postures | AB27: 0.25 | AD27: 0.25 | AE27: =100%-(Z27+AB27+AD27) -> 0.25 | AF27: =S27*AE27 -> 0.75 | AG27: =HLOOKUP($AF27,Cotation!$I$5:$M$10,'Risk Register'!U27,(TRUE)) -> F
B28: Travaux mécaniques | C28: Montage / démontage de brides | G28: x | H28: x | I28: x | J28: x | M28: Projection de liquide / choc heurt / pincement / chute d'objet / gestes et postures | N28: 09. Risques liés aux équipements de travail | O28: Canalisation | P28: dégradé | Q28: 1 | R28: 2 | S28: =Q28+R28 -> 3 | T28: 2 | U28: =VLOOKUP($T28,Cotation!$G$6:$H$10,2,(FALSE)) -> 5 | V28: =HLOOKUP($S28,Cotation!$I$5:$M$10,'Risk Register'!U28,(TRUE)) -> F | W28: non | X28: Règle 1 - Autorisation de Travail ( compétence) Regle 2 - Consignation | Y28: Casque / casquette coquéex Chaussures de sécurité gants de manutention Lunette de sécurité | Z28: 0.25 | AA28: Habiitation BR pour les consignations électriques | AB28: 0.25 | AC28: Autorisation prélable aux travaux de démontage Consignation préalable des équipements électriques Fermeture et condamnation des vannes / purge des réseaux Elemination des energies residuelles Vérification prélabale des outillages | AD28: 0.25 | AE28: =100%-(Z28+AB28+AD28) -> 0.25 | AF28: =S28*AE28 -> 0.75 | AG28: =HLOOKUP($AF28,Cotation!$I$5:$M$10,'Risk Register'!U28,(TRUE)) -> F
B29: Travaux mécaniques | C29: Travaux mécaniques sur tuyauterie - remplacement de vanne par exemple | G29: x | H29: x | I29: x | J29: x | M29: Projection de liquide / choc heurt / pincement / chute d'objet / electrisation / gestes et postures | N29: 09. Risques liés aux équipements de travail | O29: Canalisation | P29: dégradé | Q29: 1 | R29: 2 | S29: =Q29+R29 -> 3 | T29: 2 | U29: =VLOOKUP($T29,Cotation!$G$6:$H$10,2,(FALSE)) -> 5 | V29: =HLOOKUP($S29,Cotation!$I$5:$M$10,'Risk Register'!U29,(TRUE)) -> F | W29: non | X29: Règle 1 - Autorisation de Travail ( compétence) Regle 2 - Consignation | Y29: Casque / Chaussure de sécurité / gants de travail / lunettes de sécurité Kit de consignation Balisage de la zone de travail | Z29: 0.25 | AA29: non | AB29: 0 | AC29: Autorisation prélable aux travaux de démontage Consignation préalable des équipements électriques Fermeture et condamnation des vannes / purge des réseaux Elemination des energies residuelles Vérification prélabale des outillages | AD29: 0.25 | AE29: =100%-(Z29+AB29+AD29) -> 0.5 | AF29: =S29*AE29 -> 1.5 | AG29: =HLOOKUP($AF29,Cotation!$I$5:$M$10,'Risk Register'!U29,(TRUE)) -> F
B30: Travaux électriques | C30: Raccordement électrique | G30: x | H30: x | M30: Electrisation / électrocution | N30: 14. Risques liés à l'électricité | O30: Câble / Matériel électrique | P30: Normal | Q30: 3 | R30: 3 | S30: =Q30+R30 -> 6 | T30: 4 | U30: =VLOOKUP($T30,Cotation!$G$6:$H$10,2,(FALSE)) -> 3 | V30: =HLOOKUP($S30,Cotation!$I$5:$M$10,'Risk Register'!U30,(TRUE)) -> S | W30: Mesure de conception des installations électriques selon norme NFC 15100 | X30: Règle 1 - Autorisation de Travail ( compétence) Regle 2 - Consignation Règle 3 - travaux électrique | Y30: Casque électricien Gants électricien Vêtement de travail (arc flash et Atex si possible) Chaussures de sécurité Tapis isolant Kit de consignation VAT Balisage | Z30: 0.25 | AA30: Habilitation B1 minimum Coordinateur : Formation PTW travaux electrique | AB30: 0.25 | AC30: Analyse de risque dynmaique ou RAD Permis de travail electrique signé Consignation des énergies EA : verification des compétences | AD30: 0.25 | AE30: =100%-(Z30+AB30+AD30) -> 0.25 | AF30: =S30*AE30 -> 1.5 | AG30: =HLOOKUP($AF30,Cotation!$I$5:$M$10,'Risk Register'!U30,(TRUE)) -> M
B31: Travaux électriques | C31: Remplacement d'intérrupteur / remplacement de prise | H31: x | M31: Electrisation / électrocution | N31: 14. Risques liés à l'électricité | O31: Prise / interrupteur | P31: Normal | Q31: 3 | R31: 3 | S31: =Q31+R31 -> 6 | T31: 4 | U31: =VLOOKUP($T31,Cotation!$G$6:$H$10,2,(FALSE)) -> 3 | V31: =HLOOKUP($S31,Cotation!$I$5:$M$10,'Risk Register'!U31,(TRUE)) -> S | W31: Mesure de conception des installations électriques selon norme NFC 15100 | X31: Règle 1 - Autorisation de Travail ( compétence) Regle 2 - Consignation Règle 3 - travaux électrique | Y31: Casque électricien Gants électricien Vêtement de travail (arc flash et Atex si possible) Chaussures de sécurité Tapis isolant Kit de consignation VAT Balisage | Z31: 0.25 | AA31: Habilitation BS minimum Coordinateur : Formation PTW travaux electrique | AB31: 0.25 | AC31: Analyse de risque dynmaique ou RAD Permis de travail electrique signé Consignation des énergies EA : verification des compétences | AD31: 0.25 | AE31: =100%-(Z31+AB31+AD31) -> 0.25 | AF31: =S31*AE31 -> 1.5 | AG31: =HLOOKUP($AF31,Cotation!$I$5:$M$10,'Risk Register'!U31,(TRUE)) -> M
B32: Bricolage | C32: Travaux de serrurerie | G32: x | H32: x | J32: x | M32: Coupure / heurt | N32: 09. Risques liés aux équipements de travail | O32: Outillage manuel ou électroportatif | P32: Normal | Q32: 2 | R32: 3 | S32: =Q32+R32 -> 5 | T32: 2 | U32: =VLOOKUP($T32,Cotation!$G$6:$H$10,2,(FALSE)) -> 5 | V32: =HLOOKUP($S32,Cotation!$I$5:$M$10,'Risk Register'!U32,(TRUE)) -> M | W32: N/A | X32: non | Y32: Chaussures de sécurité / Gants de manutention / Lunettes de sécurité | Z32: 0.25 | AA32: Non | AB32: 0 | AC32: Analyse de risque préalbale et vérification du bon fonctionnement et de la présence de tout les éléments de sécurité sur les outils | AD32: 0.25 | AE32: =100%-(Z32+AB32+AD32) -> 0.5 | AF32: =S32*AE32 -> 2.5 | AG32: =HLOOKUP($AF32,Cotation!$I$5:$M$10,'Risk Register'!U32,(TRUE)) -> F
B33: Bricolage | C33: Montage / démontage de meuble | G33: x | H33: x | J33: x | M33: Coupure / heurt | N33: 05. Risques liés à la manutention manuelle de charge | O33: Mobilier / outillage manuel ou électroportaif | P33: Normal | Q33: 3 | R33: 2 | S33: =Q33+R33 -> 5 | T33: 3 | U33: =VLOOKUP($T33,Cotation!$G$6:$H$10,2,(FALSE)) -> 4 | V33: =HLOOKUP($S33,Cotation!$I$5:$M$10,'Risk Register'!U33,(TRUE)) -> M | W33: N/A | X33: non | Y33: Chaussures de sécurité / Gants de manutention / Lunettes de sécurité | Z33: 0.25 | AA33: Formation gestes et postures | AB33: 0.1 | AC33: Procédure manual handling | AD33: 0.1 | AE33: =100%-(Z33+AB33+AD33) -> 0.55 | AF33: =S33*AE33 -> 2.75 | AG33: =HLOOKUP($AF33,Cotation!$I$5:$M$10,'Risk Register'!U33,(TRUE)) -> M
B34: Relevés et mesures | C34: Recherche de fuite sur groupe froid | I34: x | N34: 14. Risques liés à l'électricité | O34: Groupe Froid | P34: Normal | Q34: 2 | R34: 1 | S34: =Q34+R34 -> 3 | T34: 2 | U34: =VLOOKUP($T34,Cotation!$G$6:$H$10,2,(FALSE)) -> 5 | V34: =HLOOKUP($S34,Cotation!$I$5:$M$10,'Risk Register'!U34,(TRUE)) -> F | W34: Sonde de détection fixesur les groupe de capacité supérieur à 500KG | X34: Règle 1 - Autorisation de Travail ( compétence) Regle 2 - Consignation Règle 3 - travaux électrique | Y34: Vêtement de travail couvrant Gants de protection chimique vérifier les EPI recommandés de la FDS au préalable Rubrique 8 / Lunette de sécurité. | Z34: 0.25 | AA34: Habilitation BS minimum Etre titulaire d'une attestation de capacité de niveau I pour les frigoriste | AB34: 0.25 | AC34: Analyse de risque dynmaique ou RAD Permis de travail electrique signé Consignation des énergies EA : verification des compétences | AD34: 0.25 | AE34: =100%-(Z34+AB34+AD34) -> 0.25 | AF34: =S34*AE34 -> 0.75 | AG34: =HLOOKUP($AF34,Cotation!$I$5:$M$10,'Risk Register'!U34,(TRUE)) -> F
B35: Exposition aux produits chimiques | C35: Remplacement de fluide frigorigène | I35: x | M35: Projection de produits chimiques / Inhalation de vapeurs chimiques / brûlure | N35: 07. Risques liés aux produits chimiques, aux émissions et aux déchets | O35: Fluide frigorigène | P35: Normal | Q35: 1 | R35: 1 | S35: =Q35+R35 -> 2 | T35: 3 | U35: =VLOOKUP($T35,Cotation!$G$6:$H$10,2,(FALSE)) -> 4 | V35: =HLOOKUP($S35,Cotation!$I$5:$M$10,'Risk Register'!U35,(TRUE)) -> M | W35: non | X35: non | Y35: Vêtement de travail couvrant Gants de protection chimique vérifier les EPI recommandés de la FDS au préalable Rubrique 8 Lunette de sécurité. | Z35: 0.25 | AA35: Etre titulaire d'une attestation de capacité de niveau I pour les frigoriste | AB35: 0.25 | AC35: FDS des produits utilisés Procedure substance dangeureuse COSH Alayse de risque produit chimique Seirich Respect strict des consignes de tri Attention aux mélange de déchets incompatibles Déclaration aux autorités des quantités par type de fluide évacué | AD35: 0.25 | AE35: =100%-(Z35+AB35+AD35) -> 0.25 | AF35: =S35*AE35 -> 0.5 | AG35: =HLOOKUP($AF35,Cotation!$I$5:$M$10,'Risk Register'!U35,(TRUE)) -> F
B36: Exposition aux produits chimiques | C36: Manipulation de déchets dangereux | H36: x | I36: x | J36: x | M36: Projection de produits chimiques / Inhalation de vapeurs chimiques / brûlure | N36: 07. Risques liés aux produits chimiques, aux émissions et aux déchets | O36: Déchets dangereux | P36: Normal | Q36: 2 | R36: 1 | S36: =Q36+R36 -> 3 | T36: 3 | U36: =VLOOKUP($T36,Cotation!$G$6:$H$10,2,(FALSE)) -> 4 | V36: =HLOOKUP($S36,Cotation!$I$5:$M$10,'Risk Register'!U36,(TRUE)) -> M | W36: non | X36: non | Y36: Vêtement de travail couvrant Gants de protection chimique vérifier les EPI recommandés de la FDS au préalable Rubrique 8 Lunette de sécurité. | Z36: 0.25 | AA36: Coresafety training : Sensibilisation à la manipulation des produits chimiques | AB36: 0.25 | AC36: FDS des produits utilisés Alayse de risque produit chimique Seirich Respect strict des consignes de tri Attention aux mélange de déchets incompatibles Déclaration aux autorités des quantités par type de dechets | AD36: 0.25 | AE36: =100%-(Z36+AB36+AD36) -> 0.25 | AF36: =S36*AE36 -> 0.75 | AG36: =HLOOKUP($AF36,Cotation!$I$5:$M$10,'Risk Register'!U36,(TRUE)) -> F
B37: Exposition aux produits chimiques | C37: Stockage de déchets liquides dangereux | H37: x | I37: x | J37: x | M37: Projection de produits chimiques / Inhalation de vapeurs chimiques / brûlure | N37: 07. Risques liés aux produits chimiques, aux émissions et aux déchets | O37: Liquides et produits chimiques étiquetés dangereux | P37: Normal | Q37: 2 | R37: 1 | S37: =Q37+R37 -> 3 | T37: 3 | U37: =VLOOKUP($T37,Cotation!$G$6:$H$10,2,(FALSE)) -> 4 | V37: =HLOOKUP($S37,Cotation!$I$5:$M$10,'Risk Register'!U37,(TRUE)) -> M | W37: non | X37: non | Y37: Vêtement de travail couvrant Gants de protection chimique vérifier les EPI recommandés de la FDS au préalable Rubrique 8 Lunette de sécurité. | Z37: 0.25 | AA37: Coresafety training : Sensibilisation à la manipulation des produits chimiques | AB37: 0.25 | AC37: FDS des produits utilisés Procedure substance dangeureuse COSH Alayse de risque produit chimique Seirich Respect strict des consignes de tri Attention aux mélange de déchets incompatibles Déclaration aux autorités des quantités par type de dechets Produits sur rétention | AD37: 0.25 | AE37: =100%-(Z37+AB37+AD37) -> 0.25 | AF37: =S37*AE37 -> 0.75 | AG37: =HLOOKUP($AF37,Cotation!$I$5:$M$10,'Risk Register'!U37,(TRUE)) -> F
B38: Exposition aux produits chimiques | C38: Stockage de produits chimiques | H38: x | I38: x | J38: x | M38: Projection de produits chimiques / Inhalation de vapeurs chimiques / brûlure | N38: 07. Risques liés aux produits chimiques, aux émissions et aux déchets | O38: Liquides et produits chimiques étiquetés dangereux / Cuve / IBC / Bidons | P38: Normal | Q38: 5 | R38: 2 | S38: =Q38+R38 -> 7 | T38: 3 | U38: =VLOOKUP($T38,Cotation!$G$6:$H$10,2,(FALSE)) -> 4 | V38: =HLOOKUP($S38,Cotation!$I$5:$M$10,'Risk Register'!U38,(TRUE)) -> S | W38: Compatibilité des matériaux et étiquetage des produits | X38: non | Y38: Vêtement de travail couvrant Gants de protection chimique vérifier les EPI recommandés de la FDS au préalable Rubrique 8 Lunette de sécurité. | Z38: 0.25 | AA38: Coresafety training : Sensibilisation à la manipulation des produits chimiques | AB38: 0.25 | AC38: FDS des produits utilisés Procedure substance dangeureuse COSH Alayse de risque produit chimique Seirich Respect strict des consignes de tri Attention aux mélange de déchets incompatibles Déclaration aux autorités des quantités par type de dechets Produits sur rétention | AD38: 0.25 | AE38: =100%-(Z38+AB38+AD38) -> 0.25 | AF38: =S38*AE38 -> 1.75 | AG38: =HLOOKUP($AF38,Cotation!$I$5:$M$10,'Risk Register'!U38,(TRUE)) -> F
B39: Exposition aux produits chimiques | C39: Utilisation de colle / vernis / peinture | G39: x | H39: x | I39: x | J39: x | M39: Projection de produits chimiques / Inhalation de vapeurs chimiques / brûlure | N39: 07. Risques liés aux produits chimiques, aux émissions et aux déchets | O39: Colle / vernis / peinture | P39: Normal | Q39: 4 | R39: 1 | S39: =Q39+R39 -> 5 | T39: 2 | U39: =VLOOKUP($T39,Cotation!$G$6:$H$10,2,(FALSE)) -> 5 | V39: =HLOOKUP($S39,Cotation!$I$5:$M$10,'Risk Register'!U39,(TRUE)) -> M | W39: Compatibilité des matériaux et étiquetage des produits | X39: non | Y39: Vêtement de travail couvrant Gants de protection chimique vérifier les EPI recommandés de la FDS au préalable Rubrique 8 Lunette de sécurité. | Z39: 0.25 | AA39: Coresafety training : Sensibilisation à la manipulation des produits chimiques | AB39: 0.25 | AC39: FDS des produits utilisés Procedure substance dangeureuse COSH Alayse de risque produit chimique Seirich Respect strict des consignes de tri Attention aux mélange de déchets incompatibles Déclaration aux autorités des quantités par type de dechets Produits sur rétention | AD39: 0.25 | AE39: =100%-(Z39+AB39+AD39) -> 0.25 | AF39: =S39*AE39 -> 1.25 | AG39: =HLOOKUP($AF39,Cotation!$I$5:$M$10,'Risk Register'!U39,(TRUE)) -> F
B40: Exposition aux produits chimiques | C40: Utilisation de solvant | G40: x | H40: x | I40: x | J40: x | M40: Projection de solvant / Inhalation de COV / brûlure / incendie | N40: 07. Risques liés aux produits chimiques, aux émissions et aux déchets | O40: Solvant | P40: Normal | Q40: 4 | R40: 1 | S40: =Q40+R40 -> 5 | T40: 3 | U40: =VLOOKUP($T40,Cotation!$G$6:$H$10,2,(FALSE)) -> 4 | V40: =HLOOKUP($S40,Cotation!$I$5:$M$10,'Risk Register'!U40,(TRUE)) -> M | W40: Compatibilité des matériaux et étiquetage des produits | X40: non | Y40: Vêtement de travail couvrant Gants de protection chimique vérifier les EPI recommandés de la FDS au préalable Rubrique 8 Lunette de sécurité. | Z40: 0.25 | AA40: Coresafety training : Sensibilisation à la manipulation des produits chimiques | AB40: 0.25 | AC40: FDS des produits utilisés Procedure substance dangeureuse COSH Alayse de risque produit chimique Seirich Respect strict des consignes de tri Attention aux mélange de déchets incompatibles Déclaration aux autorités des quantités par type de dechets Produits sur rétention | AD40: 0.25 | AE40: =100%-(Z40+AB40+AD40) -> 0.25 | AF40: =S40*AE40 -> 1.25 | AG40: =HLOOKUP($AF40,Cotation!$I$5:$M$10,'Risk Register'!U40,(TRUE)) -> F
B41: Exposition aux produits chimiques | C41: Utilisation de lubrifiant | G41: x | H41: x | I41: x | J41: x | M41: Projection de lubrifiant / Chute et glissade / incendie | N41: 07. Risques liés aux produits chimiques, aux émissions et aux déchets | O41: Lubrifiant | P41: Normal | Q41: 4 | R41: 1 | S41: =Q41+R41 -> 5 | T41: 2 | U41: =VLOOKUP($T41,Cotation!$G$6:$H$10,2,(FALSE)) -> 5 | V41: =HLOOKUP($S41,Cotation!$I$5:$M$10,'Risk Register'!U41,(TRUE)) -> M | W41: Compatibilité des matériaux et étiquetage des produits | X41: non | Y41: Vêtement de travail couvrant Gants de protection chimique vérifier les EPI recommandés de la FDS au préalable Rubrique 8 Lunette de sécurité. | Z41: 0.25 | AA41: Coresafety training : Sensibilisation à la manipulation des produits chimiques | AB41: 0.25 | AC41: FDS des produits utilisés Procedure substance dangeureuse COSH Alayse de risque produit chimique Seirich Respect strict des consignes de tri Attention aux mélange de déchets incompatibles Déclaration aux autorités des quantités par type de dechets Produits sur rétention | AD41: 0.25 | AE41: =100%-(Z41+AB41+AD41) -> 0.25 | AF41: =S41*AE41 -> 1.25 | AG41: =HLOOKUP($AF41,Cotation!$I$5:$M$10,'Risk Register'!U41,(TRUE)) -> F
B42: Exposition aux produits chimiques | C42: Remplissage de cuve en réactif chimique | H42: x | J42: x | M42: Projection de produits chimiques / Inhalation de vapeurs chimiques / brûlure | N42: 07. Risques liés aux produits chimiques, aux émissions et aux déchets | O42: Cuve de réactif chimique | P42: Normal | Q42: 1 | R42: 1 | S42: =Q42+R42 -> 2 | T42: 3 | U42: =VLOOKUP($T42,Cotation!$G$6:$H$10,2,(FALSE)) -> 4 | V42: =HLOOKUP($S42,Cotation!$I$5:$M$10,'Risk Register'!U42,(TRUE)) -> M | W42: Compatibilité des matériaux et étiquetage des produits / cuve double peau | X42: non | Y42: Vêtement de travail couvrant Gants de protection chimique vérifier les EPI recommandés de la FDS au préalable Rubrique 8 Lunette de sécurité. | Z42: 0.25 | AA42: Coresafety training : Sensibilisation à la manipulation des produits chimiques | AB42: 0.25 | AC42: FDS des produits utilisés Procedure substance dangeureuse COSH Alayse de risque produit chimique Seirich Respect strict des consignes de tri Attention aux mélange de déchets incompatibles Déclaration aux autorités des quantités par type de dechets Produits sur rétention | AD42: 0.25 | AE42: =100%-(Z42+AB42+AD42) -> 0.25 | AF42: =S42*AE42 -> 0.5 | AG42: =HLOOKUP($AF42,Cotation!$I$5:$M$10,'Risk Register'!U42,(TRUE)) -> F
B43: Exposition aux produits chimiques | C43: Manipulation de canne d'aspiration de réactif chimique | H43: x | J43: x | M43: Projection de produits chimiques / Inhalation de vapeurs chimiques / brûlure | N43: 07. Risques liés aux produits chimiques, aux émissions et aux déchets | O43: Canne d'aspiration de réactif chimique | P43: Normal | Q43: 1 | R43: 1 | S43: =Q43+R43 -> 2 | T43: 3 | U43: =VLOOKUP($T43,Cotation!$G$6:$H$10,2,(FALSE)) -> 4 | V43: =HLOOKUP($S43,Cotation!$I$5:$M$10,'Risk Register'!U43,(TRUE)) -> M | W43: Matériel CE et compatible avec produit | X43: non | Y43: Vêtement de travail couvrant Gants de protection chimique vérifier les EPI recommandés de la FDS au préalable Rubrique 8 Lunette de sécurité. | Z43: 0.25 | AA43: Coresafety training : Sensibilisation à la manipulation des produits chimiques | AB43: 0.25 | AC43: FDS des produits utilisés Procedure substance dangeureuse COSH Alayse de risque produit chimique Seirich Respect strict des consignes de tri Attention aux mélange de déchets incompatibles Déclaration aux autorités des quantités par type de dechets Produits sur rétention | AD43: 0.25 | AE43: =100%-(Z43+AB43+AD43) -> 0.25 | AF43: =S43*AE43 -> 0.5 | AG43: =HLOOKUP($AF43,Cotation!$I$5:$M$10,'Risk Register'!U43,(TRUE)) -> F
B44: Travaux en hauteur | C44: Travaux sur pirl | G44: x | H44: x | I44: x | J44: x | M44: chute de hauteur | N44: 02. Risques de chutes de hauteur | O44: Pirl | P44: Normal | Q44: 3 | R44: 1 | S44: =Q44+R44 -> 4 | T44: 4 | U44: =VLOOKUP($T44,Cotation!$G$6:$H$10,2,(FALSE)) -> 3 | V44: =HLOOKUP($S44,Cotation!$I$5:$M$10,'Risk Register'!U44,(TRUE)) -> S | W44: PIRL conforme EN 131 (pas de défault structurel, présence des patins anti-dérapant) | X44: Règle 1 - Autorisation de Travail ( compétence) Regle 5 - Travail en hauteur | Y44: Casquette coquée Chaussure de sécurité Gants Lunettes de sécurité Balisage de la zone | Z44: 0.25 | AA44: Core safety training : elearning Formation PTW : Travaux en hauteur au dessus de 1,8 m | AB44: 0 | AC44: Analyse de risque avant travaux ou RAD Inspection mensuelle WAHSa Vérification de l'équipement avant utilisation (état de conservation, présence de l'ensemble des pièces, stabilité) Matériel ressencé et référencé Permis de travail en hauteur pour les hauteurs de plus de 1,80 signé EA : verification des compétences | AD44: 0.25 | AE44: =100%-(Z44+AB44+AD44) -> 0.5 | AF44: =S44*AE44 -> 2 | AG44: =HLOOKUP($AF44,Cotation!$I$5:$M$10,'Risk Register'!U44,(TRUE)) -> M
B45: Travaux en hauteur | C45: Accès en hauteur à l'aide d'une échelle | G45: x | H45: x | I45: x | J45: x | K45: x | M45: Chute de hauteur / chute d'objet | N45: 02. Risques de chutes de hauteur | O45: Echelle | P45: Normal | Q45: 1 | R45: 3 | S45: =Q45+R45 -> 4 | T45: 4 | U45: =VLOOKUP($T45,Cotation!$G$6:$H$10,2,(FALSE)) -> 3 | V45: =HLOOKUP($S45,Cotation!$I$5:$M$10,'Risk Register'!U45,(TRUE)) -> S | W45: Echelle conforme EN 131 (pas de défault structurel, présence des patins anti-dérapant) | X45: Règle 1 - Autorisation de Travail ( compétence) Regle 5 - Travail en hauteur | Y45: Casquette coquée Chaussure de sécurité Gants Lunettes de sécurité Balisage de la zone | Z45: 0.25 | AA45: Non | AB45: 0.25 | AC45: L'échelle n'est qu'un moyen d'accès - Elle doit faire l'objet d'une vérifcation pralable et être attachée en tête - Présence d'un second opérateur Analyse de risque avant travaux ou RAD Inspection mensuelle WAHSa Vérification de l'équipement avant utilisation (état de conservation, présence de l'ensemble des pièces, stabilité) Matériel ressencé et référencé Permis de travail en hauteur pour les hauteurs de plus de 1,80 signé EA : verification des compétences | AD45: 0.25 | AE45: =100%-(Z45+AB45+AD45) -> 0.25 | AF45: =S45*AE45 -> 1 | AG45: =HLOOKUP($AF45,Cotation!$I$5:$M$10,'Risk Register'!U45,(TRUE)) -> M
B46: Travaux de soudure | C46: Soudure à l'arc | G46: x | H46: x | I46: x | J46: x | M46: Brulure / incendie / explosion | N46: 13. Risques d'incendie, d'explosion | O46: Chariot soudeur | P46: Normal | Q46: 1 | R46: 3 | S46: =Q46+R46 -> 4 | T46: 5 | U46: =VLOOKUP($T46,Cotation!$G$6:$H$10,2,(FALSE)) -> 2 | V46: =HLOOKUP($S46,Cotation!$I$5:$M$10,'Risk Register'!U46,(TRUE)) -> S | W46: Equiepement CE | X46: Règle 1 - Autorisation de Travail ( compétence) Regle 7 - travail par point chaud | Y46: EPI du soudeur gants épais en cuir casque de soudage à cristaux liquides vêtements en coton ignifugé vérifier les EPI recommandés de la FDS au préalable Rubrique 8 | Z46: 0.25 | AA46: Formation soudure à l'arc Formation extincteur Core safety training : elearning Formation PTW : Travaux par point chaud | AB46: 0 | AC46: Permis de travail signé Procedure hot work Procedure PTW : Permis Feu Vérification préalable du matériel (verification avant utilisation / inspection annuelle) Procedure soudure à l'arc EA : Verification de compétences | AD46: 0.25 | AE46: =100%-(Z46+AB46+AD46) -> 0.5 | AF46: =S46*AE46 -> 2 | AG46: =HLOOKUP($AF46,Cotation!$I$5:$M$10,'Risk Register'!U46,(TRUE)) -> S
B47: Travaux de soudure | C47: Soudure par brassage | G47: x | H47: x | I47: x | J47: x | M47: Brulure / incendie / explosion | N47: 13. Risques d'incendie, d'explosion | O47: Chariot soudeur | P47: Normal | Q47: 1 | R47: 3 | S47: =Q47+R47 -> 4 | T47: 3 | U47: =VLOOKUP($T47,Cotation!$G$6:$H$10,2,(FALSE)) -> 4 | V47: =HLOOKUP($S47,Cotation!$I$5:$M$10,'Risk Register'!U47,(TRUE)) -> M | W47: Equiepement CE | X47: Règle 1 - Autorisation de Travail ( compétence) Regle 7 - travail par point chaud | Y47: EPI du soudeur gants épais en cuir casque de soudage à cristaux liquides vêtements en coton ignifugé | Z47: 0.25 | AA47: Formation soudure à l'arc Formation extincteur Core safety training : elearning Formation PTW : Travaux par point chaud | AB47: 0.25 | AC47: Permis de travail signé Procedure hot work Procedure PTW : Permis Feu Vérification préalable du matériel (verification avant utilisation / inspection annuelle) Procedure soudure brasage EA : Verification de compétences | AD47: 0.25 | AE47: =100%-(Z47+AB47+AD47) -> 0.25 | AF47: =S47*AE47 -> 1 | AG47: =HLOOKUP($AF47,Cotation!$I$5:$M$10,'Risk Register'!U47,(TRUE)) -> F
B48: Travaux avec outils manuels | C48: Utilisation d'outil à main | H48: x | I48: x | J48: x | M48: Coupure | N48: 09. Risques liés aux équipements de travail | O48: Tournevis / clés / marteau… | P48: Normal | Q48: 4 | R48: 3 | S48: =Q48+R48 -> 7 | T48: 2 | U48: =VLOOKUP($T48,Cotation!$G$6:$H$10,2,(FALSE)) -> 5 | V48: =HLOOKUP($S48,Cotation!$I$5:$M$10,'Risk Register'!U48,(TRUE)) -> M | W48: non | X48: non | Y48: Gants anticoupure / lunettes de sécurité / Vêtements de travail / | Z48: 0.25 | AA48: non | AB48: 0 | AC48: Analyse de risque avant travaux ou RAD Vérification des outils et de leur intégrité avant utilisation | AD48: 0.25 | AE48: =100%-(Z48+AB48+AD48) -> 0.5 | AF48: =S48*AE48 -> 3.5 | AG48: =HLOOKUP($AF48,Cotation!$I$5:$M$10,'Risk Register'!U48,(TRUE)) -> F
B49: Travaux avec outils manuels | C49: Utilisation d'outil tranchant ou coupant | H49: x | I49: x | J49: x | M49: Coupure | N49: 09. Risques liés aux équipements de travail | O49: Cutter / Masicot / couteau / scie à main / grattoir munie de lame de cutter | P49: Normal | Q49: 3 | R49: 3 | S49: =Q49+R49 -> 6 | T49: 3 | U49: =VLOOKUP($T49,Cotation!$G$6:$H$10,2,(FALSE)) -> 4 | V49: =HLOOKUP($S49,Cotation!$I$5:$M$10,'Risk Register'!U49,(TRUE)) -> S | W49: Couteaux de sureté avec lames enfermées ou safety Cutter à lame rétractable uniquement | X49: non | Y49: Gants anticoupure maxicut / lunettes de sécurité / Vêtements de travail | Z49: 0.1 | AA49: non | AB49: 0 | AC49: Couteaux de sureté avec lames enfermées Vérification des outils et de leur intégrité avant utilisation Cutter interdit Cutter à lame rétractable et débrayable autorisé | AD49: 0.25 | AE49: =100%-(Z49+AB49+AD49) -> 0.65 | AF49: =S49*AE49 -> 3.9 | AG49: =HLOOKUP($AF49,Cotation!$I$5:$M$10,'Risk Register'!U49,(TRUE)) -> M
B50: Travaux en espace confiné | C50: Travail en espace confiné | H50: x | I50: x | J50: x | M50: Asphixie/ Intoxication / inhalation de gaz | N50: 19. Risques liés aux interventions en zones spécifiques (non destinées à la présence humaine, ou avec restriction d'accès) | O50: Cuves / galerie / poste de relevage | P50: dégradé | Q50: 1 | R50: 4 | S50: =Q50+R50 -> 5 | T50: 5 | U50: =VLOOKUP($T50,Cotation!$G$6:$H$10,2,(FALSE)) -> 2 | V50: =HLOOKUP($S50,Cotation!$I$5:$M$10,'Risk Register'!U50,(TRUE)) -> S | W50: Identification des espaces confinés | X50: Règle 1 - Autorisation de Travail ( compétence) Regle 6 - travailespace confiné | Y50: Casque avec jugulaire lunette de sécurité Chaussure de sécurité adaptée gants de travail Detecteur 4 gaz etaloné protection respiratoire adaptée protection contre les chutes Balisage de la zone de travail Moyen de communication | Z50: 0.25 | AA50: Formation CATEC - Certificat d'aptitude aux travaux en Espaces Confinés Formation harnais Formation PTW espace confinée | AB50: 0 | AC50: Permis de travail signé Procedure espace confinée Procedure PTW : espace confinés Vérification préalable du matériel (verification avant utilisation / inspection annuelle) EA : Verification de compétences | AD50: 0.25 | AE50: =100%-(Z50+AB50+AD50) -> 0.5 | AF50: =S50*AE50 -> 2.5 | AG50: =HLOOKUP($AF50,Cotation!$I$5:$M$10,'Risk Register'!U50,(TRUE)) -> S
B51: Travaux exposant aux intempéries | C51: Travail extérieure en période de canicule | D51: x | E51: x | F51: x | G51: x | H51: x | I51: x | J51: x | K51: x | L51: x | M51: Coup de chaud / desydratation | N51: 12. Risques liés aux ambiances thermiques | O51: Environnement extérieur | P51: Normal | Q51: 1 | R51: 3 | S51: =Q51+R51 -> 4 | T51: 3 | U51: =VLOOKUP($T51,Cotation!$G$6:$H$10,2,(FALSE)) -> 4 | V51: =HLOOKUP($S51,Cotation!$I$5:$M$10,'Risk Register'!U51,(TRUE)) -> M | W51: non | X51: non | Y51: Adapter ses vêtements aux conditions sans pour autant supprimer les EPI nécessaires pour les tâches à excécuter | Z51: 0.25 | AA51: non | AB51: 0 | AC51: Adapter les horaires de travail en fonction des conditions météos - Décaler tôt le matin les interventions extérieures en cas de canicule mesure de prevention en cas de canicule et travaux extérieur Pauses fréquentes et adaptées Réduction de la charge de travail Protection solaire et équipements Prévoir ou aménager des zones d'ombre ou des abris Fourniture d'eau pour s'hydrater abondamment | AD51: 0.25 | AE51: =100%-(Z51+AB51+AD51) -> 0.5 | AF51: =S51*AE51 -> 2 | AG51: =HLOOKUP($AF51,Cotation!$I$5:$M$10,'Risk Register'!U51,(TRUE)) -> M
B52: Travaux exposant aux intempéries | C52: Travail extéreur en période de froid | D52: x | E52: x | F52: x | G52: x | H52: x | I52: x | J52: x | K52: x | L52: x | M52: Prendre froid / gelure | N52: 12. Risques liés aux ambiances thermiques | O52: Environnement extérieur | P52: Normal | Q52: 1 | R52: 3 | S52: =Q52+R52 -> 4 | T52: 3 | U52: =VLOOKUP($T52,Cotation!$G$6:$H$10,2,(FALSE)) -> 4 | V52: =HLOOKUP($S52,Cotation!$I$5:$M$10,'Risk Register'!U52,(TRUE)) -> M | W52: non | X52: non | Y52: EPI et vêtements chauds | Z52: 0.25 | AA52: non | AB52: 0 | AC52: Vérification des conditions météos prélablement à l'opération - décaler les interventions si besoins Mise à disposition de boisson chaude Mise à dispostion de locaux chauffés Réduction de la charge de travail Pauses fréquentes et adaptées | AD52: 0.25 | AE52: =100%-(Z52+AB52+AD52) -> 0.5 | AF52: =S52*AE52 -> 2 | AG52: =HLOOKUP($AF52,Cotation!$I$5:$M$10,'Risk Register'!U52,(TRUE)) -> M
B53: Travaux exposant aux bruits | C53: Exposition au bruit | D53: x | E53: x | F53: x | G53: x | H53: x | I53: x | J53: x | K53: x | L53: x | M53: Perte d'audition | N53: 11. Risques et nuisances liés au bruit | O53: Environnement bruyant | P53: Normal | Q53: 2 | R53: 2 | S53: =Q53+R53 -> 4 | T53: 3 | U53: =VLOOKUP($T53,Cotation!$G$6:$H$10,2,(FALSE)) -> 4 | V53: =HLOOKUP($S53,Cotation!$I$5:$M$10,'Risk Register'!U53,(TRUE)) -> M | W53: Identification des équipements et zones bruyantes | X53: non | Y53: Port des protections auditives dans les zones signalées bruyantes | Z53: 0.25 | AA53: non | AB53: 0 | AC53: Obligatoire au dessus de 85db Recommandé à partir de 80db Sensibilisation du personnel Identification des zones à risque (cartographie) Identification des équipements/véhicules bruyants nécessitant le port d’EPI pour l’utilisateur Suppression de la source de bruit lorsque cela est possible (mise à l'arret de l'équipement bruyant) Si impossible : Limitation de la durée d’exposition (X heures/jours) Port des EPI (casques/protections auditives) | AD53: 0.25 | AE53: =100%-(Z53+AB53+AD53) -> 0.5 | AF53: =S53*AE53 -> 2 | AG53: =HLOOKUP($AF53,Cotation!$I$5:$M$10,'Risk Register'!U53,(TRUE)) -> M
B54: Exposition à la chaleur | C54: Exposition aux équipements générant de la chaleur | G54: x | H54: x | I54: x | J54: x | M54: Brulure | N54: 09. Risques liés aux équipements de travail | O54: Equipements / machines / Tuyauteries | P54: Normal | Q54: 2 | R54: 3 | S54: =Q54+R54 -> 5 | T54: 2 | U54: =VLOOKUP($T54,Cotation!$G$6:$H$10,2,(FALSE)) -> 5 | V54: =HLOOKUP($S54,Cotation!$I$5:$M$10,'Risk Register'!U54,(TRUE)) -> M | W54: Conformité équipement | X54: non | Y54: Port des EPI classique Port de gant anti-chaleur | Z54: 0.25 | AA54: non | AB54: 0 | AC54: Signalétique des surface chaude Respect des modes opératoires existants Ne pas toucher les surfaces chaudes | AD54: 0.25 | AE54: =100%-(Z54+AB54+AD54) -> 0.5 | AF54: =S54*AE54 -> 2.5 | AG54: =HLOOKUP($AF54,Cotation!$I$5:$M$10,'Risk Register'!U54,(TRUE)) -> F
B55: Exposition à l'amiante | C55: Travail à proximité d'équipement contenant de l'amiante | F55: x | G55: x | H55: x | I55: x | J55: x | M55: Maladie professionnelle | N55: 07. Risques liés aux produits chimiques, aux émissions et aux déchets | O55: Faux plafonds / Sol / isolations de bâtiment / Elements de tuyauteries… | P55: dégradé | Q55: 1 | R55: 1 | S55: =Q55+R55 -> 2 | T55: 4 | U55: =VLOOKUP($T55,Cotation!$G$6:$H$10,2,(FALSE)) -> 3 | V55: =HLOOKUP($S55,Cotation!$I$5:$M$10,'Risk Register'!U55,(TRUE)) -> M | W55: DTA et cartogrpahie et repérage effecuée | X55: Amiante | Y55: Obligation de droit de retrait EPI masque FFP3 | Z55: 0.25 | AA55: Sensibilisation interne | AB55: 0.1 | AC55: Travaux sur amiante interdit Se référer préalablement au DTA pour identifier les zones / matériaux contenant de l'amiante / Respect stricte des affichages Pour tout travail sur matériaux amianté => consulter une entreprise spécialisé via le client | AD55: 0.25 | AE55: =100%-(Z55+AB55+AD55) -> 0.4 | AF55: =S55*AE55 -> 0.8 | AG55: =HLOOKUP($AF55,Cotation!$I$5:$M$10,'Risk Register'!U55,(TRUE)) -> M
B56: Travaux en atmosphère poussiéreuse | C56: Exposition à la poussière | G56: x | H56: x | I56: x | J56: x | M56: Inhalation de poussière / Maladie professionnelle | N56: 07. Risques liés aux produits chimiques, aux émissions et aux déchets | O56: Matériel électroportatif essentiellement | P56: normal | Q56: 2 | R56: 1 | S56: =Q56+R56 -> 3 | T56: 3 | U56: =VLOOKUP($T56,Cotation!$G$6:$H$10,2,(FALSE)) -> 4 | V56: =HLOOKUP($S56,Cotation!$I$5:$M$10,'Risk Register'!U56,(TRUE)) -> M | W56: Ventilation des espaces d'intervention | X56: non | Y56: Casquette coquée Chaussure de sécurité Gants Lunettes de sécurité Masque FFP3 | Z56: 0.25 | AA56: non | AB56: 0 | AC56: Actions de sensibilisation/préparation : - Sensibilisation à la selection et au port du masque (étanchiété) - Examen du type de la poussière (Par exemple : via seirich, etc) si necessaire demandé FDS - Rédaction d'un mode opératoire spécifique Actions Techniques : - Bonne ventilation. - Interdiction de fumer. - Nettoyage régulier des chantiers - Evacuation des gravats ou déchets - Aspiration des poussières - Port de masque anti-poussières. - Utilisation de détecteurs adaptés si necessaire. - Limiter la durée d'exposition en fonction de l'évaluation du risque (X heures / jours). | AD56: 0.25 | AE56: =100%-(Z56+AB56+AD56) -> 0.5 | AF56: =S56*AE56 -> 1.5 | AG56: =HLOOKUP($AF56,Cotation!$I$5:$M$10,'Risk Register'!U56,(TRUE)) -> F
B57: Bricolage | C57: Remplacement de dalle de faux plafond | H57: x | J57: x | M57: Chute de hauteur / chute d'objet | N57: 02. Risques de chutes de hauteur | O57: Pirl / escabeau / nacelle / échaffaudage | P57: Normal | Q57: 3 | R57: 2 | S57: =Q57+R57 -> 5 | T57: 3 | U57: =VLOOKUP($T57,Cotation!$G$6:$H$10,2,(FALSE)) -> 4 | V57: =HLOOKUP($S57,Cotation!$I$5:$M$10,'Risk Register'!U57,(TRUE)) -> M | W57: Equipement EN 131 | X57: Règle 1 - Autorisation de Travail ( compétence) Regle 5 - Travail en hauteur | Y57: Casquette coquée Chaussure de sécurité Gants Lunettes de sécurité Masque pourla poussière Mise en place d'un balisage | Z57: 0.25 | AA57: Core safety training : elearning Formation PTW : Travaux en hauteur au dessus de 1,8 m Si echaffaudage:formation montage / demaontage | AB57: 0 | AC57: Analyse de risque avant travaux ou RAD Inspection mensuelle WAHSa Vérification de l'équipement avant utilisation (état de conservation, présence de l'ensemble des pièces, stabilité) Matériel ressencé et référencé Permis de travail en hauteur pour les hauteurs de plus de 1,80 signé EA : verification des compétences | AD57: 0.25 | AE57: =100%-(Z57+AB57+AD57) -> 0.5 | AF57: =S57*AE57 -> 2.5 | AG57: =HLOOKUP($AF57,Cotation!$I$5:$M$10,'Risk Register'!U57,(TRUE)) -> M
B58: Relevés et mesures | C58: Recherche dans les faux plafond (branchement / fuite…) | G58: x | H58: x | I58: x | J58: x | M58: Chute de hauteur / chute d'objet | N58: 02. Risques de chutes de hauteur | O58: Pirl / escabeau / nacelle / échaffaudage | P58: Normal | Q58: 2 | R58: 2 | S58: =Q58+R58 -> 4 | T58: 4 | U58: =VLOOKUP($T58,Cotation!$G$6:$H$10,2,(FALSE)) -> 3 | V58: =HLOOKUP($S58,Cotation!$I$5:$M$10,'Risk Register'!U58,(TRUE)) -> S | W58: Equipement EN 131 | X58: Règle 1 - Autorisation de Travail ( compétence) Regle 5 - Travail en hauteur | Y58: Casquette coquée Chaussure de sécurité Gants Lunettes de sécurité Masque pour la poussière Mise en place d'un balisage | Z58: 0.1 | AA58: Core safety training : elearning Formation PTW : Travaux en hauteur au dessus de 1,8 m Si echaffaudage:formation montage / demaontage | AB58: 0 | AC58: Analyse de risque avant travaux ou RAD Inspection mensuelle WAHSa Vérification de l'équipement avant utilisation (état de conservation, présence de l'ensemble des pièces, stabilité) Matériel ressencé et référencé Permis de travail en hauteur pour les hauteurs de plus de 1,80 signé EA : verification des compétences | AD58: 0 | AE58: =100%-(Z58+AB58+AD58) -> 0.9 | AF58: =S58*AE58 -> 3.6 | AG58: =HLOOKUP($AF58,Cotation!$I$5:$M$10,'Risk Register'!U58,(TRUE)) -> M
B59: Exposition aux produits chimiques | C59: Remplissage de cuve en réactif chimique | H59: x | M59: Projection de produits chimiques / Inhalation de vapeurs chimiques / brûlure | N59: 07. Risques liés aux produits chimiques, aux émissions et aux déchets | O59: Cuve de réactif chimique | P59: Normal | Q59: 1 | R59: 2 | S59: =Q59+R59 -> 3 | T59: 3 | U59: =VLOOKUP($T59,Cotation!$G$6:$H$10,2,(FALSE)) -> 4 | V59: =HLOOKUP($S59,Cotation!$I$5:$M$10,'Risk Register'!U59,(TRUE)) -> M | W59: Compatibilité des matériaux et étiquetage des produits / cuve double peau | X59: non | Y59: Vêtement de travail couvrant Gants de protection chimique vérifier les EPI recommandés de la FDS au préalable Rubrique 8 Lunette de sécurité. | Z59: 0.25 | AA59: Coresafety training : Sensibilisation à la manipulation des produits chimiques | AB59: 0.1 | AC59: FDS des produits utilisés Procedure substance dangeureuse COSH Alayse de risque produit chimique Seirich Respect strict des consignes de tri Attention aux mélange de déchets incompatibles | AD59: 0.25 | AE59: =100%-(Z59+AB59+AD59) -> 0.4 | AF59: =S59*AE59 -> 1.2 | AG59: =HLOOKUP($AF59,Cotation!$I$5:$M$10,'Risk Register'!U59,(TRUE)) -> F
B60: Manutention manuelle | C60: Rayonnage / rangement | H60: x | J60: x | M60: Chute d'objet / effondrement / TMS | N60: 05. Risques liés à la manutention manuelle de charge | O60: Armoire / rayonnage | P60: Normal | Q60: 5 | R60: 2 | S60: =Q60+R60 -> 7 | T60: 2 | U60: =VLOOKUP($T60,Cotation!$G$6:$H$10,2,(FALSE)) -> 5 | V60: =HLOOKUP($S60,Cotation!$I$5:$M$10,'Risk Register'!U60,(TRUE)) -> M | W60: Rayonnage conforme et sécurisé | X60: non | Y60: Casquette coquée Gants Lunettes de sécurité Chaussure de sécurité | Z60: 0.25 | AA60: Coresafety training :manutention mauelle | AB60: 0.25 | AC60: Eléments lourd en bas Eléments léger en haut Adopyter une démarche 5S | AD60: 0.25 | AE60: =100%-(Z60+AB60+AD60) -> 0.25 | AF60: =S60*AE60 -> 1.75 | AG60: =HLOOKUP($AF60,Cotation!$I$5:$M$10,'Risk Register'!U60,(TRUE)) -> F
B61: Travaux électriques | C61: Branchement de matériel informatique sur prise | G61: x | H61: x | M61: Electrisation / électrocution | N61: 14. Risques liés à l'électricité | O61: matériel informatique | P61: Normal | Q61: 1 | R61: 1 | S61: =Q61+R61 -> 2 | T61: 1 | U61: =VLOOKUP($T61,Cotation!$G$6:$H$10,2,(FALSE)) -> 6 | V61: =HLOOKUP($S61,Cotation!$I$5:$M$10,'Risk Register'!U61,(TRUE)) -> F | W61: Mesure de conception des installations électriques selon norme NFC 15100 | X61: non | Y61: Casquette coquée Gants Lunettes de sécurité Chaussure de sécurité | Z61: 0.25 | AA61: Coresafety training :manutention mauelle | AB61: 0.25 | AC61: Vériication préalable de l'état des équipement Procedure WKEQ | AD61: 0.25 | AE61: =100%-(Z61+AB61+AD61) -> 0.25 | AF61: =S61*AE61 -> 0.5 | AG61: =HLOOKUP($AF61,Cotation!$I$5:$M$10,'Risk Register'!U61,(TRUE)) -> F
B62: Travaux électriques | C62: Remplacement ou réparation de BAES | M62: Electrisation / électrocution | N62: 14. Risques liés à l'électricité | O62: BAES | P62: dégradé | Q62: 2 | R62: 1 | S62: =Q62+R62 -> 3 | T62: 1 | U62: =VLOOKUP($T62,Cotation!$G$6:$H$10,2,(FALSE)) -> 6 | V62: =HLOOKUP($S62,Cotation!$I$5:$M$10,'Risk Register'!U62,(TRUE)) -> F | W62: BAES isolé - matériel normé | X62: Règle 1 - Autorisation de Travail ( compétence) Regle 2 - Consignation Règle 3 - travaux électrique | Y62: Casque électricien Gants électricien Vêtement de travail (arc flash et Atex si possible) Chaussures de sécurité Tapis isolant Kit de consignation VAT Balisage | AA62: Formation : habilitation électrique indice BS Coordinateur formation PTW :Travaux electrique | AC62: Analyse de risque dynmaique ou RAD Permis de travail electrique signé Consignation des énergies EA : verification des compétences
B63: Travaux électriques | C63: Remplacement ou réparation de BAES | H63: x | J63: x | M63: Chute de hauteur / chute d'objet / électrisation | N63: 14. Risques liés à l'électricité | O63: BAES | P63: dégradé | Q63: 2 | R63: 1 | S63: =Q63+R63 -> 3 | T63: 2 | U63: =VLOOKUP($T63,Cotation!$G$6:$H$10,2,(FALSE)) -> 5 | V63: =HLOOKUP($S63,Cotation!$I$5:$M$10,'Risk Register'!U63,(TRUE)) -> F | W63: BAES isolé - matériel normé | X63: Règle 1 - Autorisation de Travail ( compétence) Regle 5 - Travail en hauteur | Y63: Casquette coquée Gants Lunettes de sécurité Chaussure de sécurité | Z63: 0.25 | AA63: Core safety training : elearning Formation PTW : Travaux en hauteur au dessus de 1,8 m Si echaffaudage:formation montage / demaontage | AB63: 0.25 | AC63: Analyse de risque avant travaux ou RAD Inspection mensuelle WAHSa Vérification de l'équipement avant utilisation (état de conservation, présence de l'ensemble des pièces, stabilité) Matériel ressencé et référencé Priviligier la PIRL Permis de travail en hauteur pour les hauteurs de plus de 1,80 signé EA : verification des compétences | AD63: 0.1 | AE63: =100%-(Z63+AB63+AD63) -> 0.4 | AF63: =S63*AE63 -> 1.2 | AG63: =HLOOKUP($AF63,Cotation!$I$5:$M$10,'Risk Register'!U63,(TRUE)) -> F
B64: Travaux électriques | C64: Branchement dans baie de brassage | G64: x | H64: x | M64: Electrisation / électrocution | N64: 14. Risques liés à l'électricité | O64: RJ45 | P64: Normal | Q64: 1 | R64: 1 | S64: =Q64+R64 -> 2 | T64: 1 | U64: =VLOOKUP($T64,Cotation!$G$6:$H$10,2,(FALSE)) -> 6 | V64: =HLOOKUP($S64,Cotation!$I$5:$M$10,'Risk Register'!U64,(TRUE)) -> F | W64: Mesure de conception des installations électriques selon norme NFC 115 | X64: Règle 1 - Autorisation de Travail ( compétence) Regle 2 - Consignation Règle 3 - travaux électrique | Y64: En fonction de la tache Non Electrique Casquette coquée Gants Lunettes de sécurité Chaussure de sécurité Electrique Casque électricien Gants électricien Vêtement de travail (arc flash et Atex si possible) Chaussures de sécurité Outillage isolé Tapis isolant Kit de consignation VAT Balisage | Z64: 0.25 | AA64: Formation : Coordinateur formation PTW :Travaux electrique Habilitation B0 / H0 permet de pénétrer dans ces zones sans intervenir directement sur les équipements électriques sous tension Habilitation BS destinée aux non-électriciens pour des interventions hors tension Habilitation BE effectuer des vérifications d'absence ou de présence de tension, ou réaliser des manœuvres spécifiques sur des équipements électriques, comme la vérification de la tension sur une carte mère ou un onduleu | AB64: 0.25 | AC64: Analyse de risque dynmaique ou RAD Permis de travail electrique signé Consignation des énergies EA : verification des compétences | AD64: 0.25 | AE64: =100%-(Z64+AB64+AD64) -> 0.25 | AF64: =S64*AE64 -> 0.5 | AG64: =HLOOKUP($AF64,Cotation!$I$5:$M$10,'Risk Register'!U64,(TRUE)) -> F
B65: Exposition aux risques biologiques | C65: Exposition à la légionnelle | D65: x | E65: x | F65: x | G65: x | H65: x | I65: x | J65: x | K65: x | L65: x | M65: Maladie professionnelle / légionnelose | N65: 08. Risques liés aux agents biologiques | O65: Tour Aéroréfrigérante | P65: Normal | Q65: 1 | R65: 1 | S65: =Q65+R65 -> 2 | T65: 3 | U65: =VLOOKUP($T65,Cotation!$G$6:$H$10,2,(FALSE)) -> 4 | V65: =HLOOKUP($S65,Cotation!$I$5:$M$10,'Risk Register'!U65,(TRUE)) -> M | X65: Règle 1 - Autorisation de Travail ( compétence) | Y65: Masque FFP3 Casquette coquée Chaussure de sécurité Gants Lunettes de sécurité | Z65: 0.25 | AA65: Formation aux risques légionnelles | AC65: Masque P3 à moins de 8m des Tour Aeroréfrigérante | AE65: =100%-(Z65+AB65+AD65) -> 0.75 | AF65: =S65*AE65 -> 1.5 | AG65: =HLOOKUP($AF65,Cotation!$I$5:$M$10,'Risk Register'!U65,(TRUE)) -> F
B66: Exposition aux risques d'emissions | C66: Travail sur équipements contenant des eaux usées | H66: x | I66: x | J66: x | M66: Projection d'eau usée, intervention de plomberie | N66: 08. Risques liés aux agents biologiques | O66: Tout équipement d'assainissemeny | P66: Normal | Q66: 4 | R66: 1 | S66: =Q66+R66 -> 5 | T66: 2 | U66: =VLOOKUP($T66,Cotation!$G$6:$H$10,2,(FALSE)) -> 5 | V66: =HLOOKUP($S66,Cotation!$I$5:$M$10,'Risk Register'!U66,(TRUE)) -> M | X66: non | Y66: Casquette coquée Chaussure de sécurité Gants chimique Lunettes de sécurité | Z66: 0.25 | AA66: Non | AC66: Consignation éllectrique des pompes/équipement si necessaire Consignation hydraulique si possible | AD66: 0.1 | AE66: =100%-(Z66+AB66+AD66) -> 0.65 | AF66: =S66*AE66 -> 3.25 | AG66: =HLOOKUP($AF66,Cotation!$I$5:$M$10,'Risk Register'!U66,(TRUE)) -> F
B67: Exposition aux risques d'emissions | C67: Travail sur équipements contenant des eaux usées | H67: x | I67: x | J67: x | M67: Projection d'eau usée / exposition à l'H2S | N67: 07. Risques liés aux produits chimiques, aux émissions et aux déchets | O67: Tout équipement d'assainissemeny | P67: Normal | Q67: 4 | R67: 1 | S67: =Q67+R67 -> 5 | T67: 3 | U67: =VLOOKUP($T67,Cotation!$G$6:$H$10,2,(FALSE)) -> 4 | V67: =HLOOKUP($S67,Cotation!$I$5:$M$10,'Risk Register'!U67,(TRUE)) -> M | X67: non | Y67: Gants manchette de protection chimique / lunettes de sécurité / vêtement couvrant Si intervention dans réseau d'assianissement => detection 4 gaz | Z67: 0.25 | AA67: Non | AB67: 0 | AC67: Consignation éllectrique des pompes/équipement si necessaire Consignation hydraulique si possible Si intervention réseau d'asssainissement : mesure d'athmosphère permanente | AD67: 0.25 | AE67: =100%-(Z67+AB67+AD67) -> 0.5 | AF67: =S67*AE67 -> 2.5 | AG67: =HLOOKUP($AF67,Cotation!$I$5:$M$10,'Risk Register'!U67,(TRUE)) -> M
B68: Travaux électriques | C68: Maintenance HT | G68: x | H68: x | L68: x | M68: Electrisation / électrocution | N68: 14. Risques liés à l'électricité | O68: Poste HT | P68: Normal | Q68: 1 | R68: 1 | S68: =Q68+R68 -> 2 | T68: 5 | U68: =VLOOKUP($T68,Cotation!$G$6:$H$10,2,(FALSE)) -> 2 | V68: =HLOOKUP($S68,Cotation!$I$5:$M$10,'Risk Register'!U68,(TRUE)) -> S | W68: Mesure de conception des installations électriques HT | X68: Règle 1 - Autorisation de Travail ( compétence) Regle 2 - Consignation Règle 3 - travaux électrique | Y68: Casque électricien Gants électricien classe 3 Vêtement de travail ignifuges et anti-arc Chaussures de sécurité isolante Tapis isolant et Tabouret Perche electrique Balisage | Z68: 0.25 | AA68: Habilitation électrique niveau HTA/HTB Coordinateur formation PTW :Travaux electrique | AB68: 0.25 | AC68: Analyse de risque dynmaique ou RAD Permis de travail electrique signé Consignation des énergies EA : verification des compétences | AD68: 0.25 | AE68: =100%-(Z68+AB68+AD68) -> 0.25 | AF68: =S68*AE68 -> 0.5 | AG68: =HLOOKUP($AF68,Cotation!$I$5:$M$10,'Risk Register'!U68,(TRUE)) -> M
B69: Travaux en hauteur | C69: Utilisation d'échafaudage fixe | G69: x | H69: x | J69: x | K69: x | M69: Chute de hauteur / chute d'objet | N69: 02. Risques de chutes de hauteur | O69: Echaffaudage | P69: Normal | Q69: 1 | R69: 1 | S69: =Q69+R69 -> 2 | T69: 4 | U69: =VLOOKUP($T69,Cotation!$G$6:$H$10,2,(FALSE)) -> 3 | V69: =HLOOKUP($S69,Cotation!$I$5:$M$10,'Risk Register'!U69,(TRUE)) -> M | W69: Equipement conforme | X69: Règle 1 - Autorisation de Travail ( compétence) Regle 5 - Travail en hauteur | Y69: Casque avec jugulaire Chaussure de sécurité Gants de travail Lunettes de sécurité | Z69: 0.25 | AB69: 0.25 | AC69: Inspecter le PV de reception:equipement conforme Analyse de risque avant travaux ou RAD Inspection journalière Vérification de l'équipement avant utilisation (état de conservation, présence de l'ensemble des pièces, stabilité) Inspection règlementaire au bout de 3 mois | AD69: 0.25 | AE69: =100%-(Z69+AB69+AD69) -> 0.25 | AF69: =S69*AE69 -> 0.5 | AG69: =HLOOKUP($AF69,Cotation!$I$5:$M$10,'Risk Register'!U69,(TRUE)) -> M
B70: Travaux en hauteur | C70: Utilisation d'échafaudage mobile | G70: x | H70: x | J70: x | K70: x | M70: Chute de hauteur / chute d'objet | N70: 02. Risques de chutes de hauteur | O70: Echaffaudage | P70: Normal | Q70: 1 | R70: 1 | S70: =Q70+R70 -> 2 | T70: 4 | U70: =VLOOKUP($T70,Cotation!$G$6:$H$10,2,(FALSE)) -> 3 | V70: =HLOOKUP($S70,Cotation!$I$5:$M$10,'Risk Register'!U70,(TRUE)) -> M | W70: Equipement conforme et CE | X70: Règle 1 - Autorisation de Travail ( compétence) Regle 5 - Travail en hauteur | Y70: Casque avec jugulaire Chaussure de sécurité Gants de travail Lunettes de sécurité | Z70: 0.25 | AA70: Core safety training : elearning Formation PTW : Travaux en hauteur au dessus de 1,8 m Si echaffaudage:formation montage / demaontage | AB70: 0.25 | AC70: Analyse de risque avant travaux ou RAD Inspection mensuelle WAHSa Vérification de l'équipement avant utilisation (état de conservation, présence de l'ensemble des pièces, stabilité) Matériel ressencé et référencé Priviligier la PIRL Permis de travail en hauteur pour les hauteurs de plus de 1,80 signé EA : verification des compétences | AD70: 0.25 | AE70: =100%-(Z70+AB70+AD70) -> 0.25 | AF70: =S70*AE70 -> 0.5 | AG70: =HLOOKUP($AF70,Cotation!$I$5:$M$10,'Risk Register'!U70,(TRUE)) -> M
B71: Travaux mécaniques | C71: Montage d'échaffaudage mobile | G71: x | H71: x | M71: Chute de hauteur Chute d'objet | N71: 02. Risques de chutes de hauteur | O71: Echaffaudage | P71: Normal | Q71: 1 | R71: 2 | S71: =Q71+R71 -> 3 | T71: 4 | U71: =VLOOKUP($T71,Cotation!$G$6:$H$10,2,(FALSE)) -> 3 | V71: =HLOOKUP($S71,Cotation!$I$5:$M$10,'Risk Register'!U71,(TRUE)) -> M | W71: Notice constructeur Equipement conforme et CE | X71: Règle 1 - Autorisation de Travail ( compétence) Regle 5 - Travail en hauteur | Y71: Casque avec jugulaire Chaussure de sécurité Gants de travail Lunettes de sécurité | Z71: 0.25 | AA71: Core safety training : elearning Formation PTW : Travaux en hauteur au dessus de 1,8 m Si echaffaudage:formation montage / demaontage | AB71: 0.25 | AC71: Analyse de risque avant travaux ou RAD Inspection mensuelle WAHSa Vérification de l'équipement avant utilisation (état de conservation, présence de l'ensemble des pièces, stabilité) Matériel ressencé et référencé Priviligier la PIRL Permis de travail en hauteur pour les hauteurs de plus de 1,80 signé EA : verification des compétences | AD71: 0.25 | AE71: =100%-(Z71+AB71+AD71) -> 0.25 | AF71: =S71*AE71 -> 0.75 | AG71: =HLOOKUP($AF71,Cotation!$I$5:$M$10,'Risk Register'!U71,(TRUE)) -> M
B72: Déplacement de plain-pied | C72: Déplacements de plain pied dans les locaux techniques | E72: x | F72: x | G72: x | H72: x | I72: x | J72: x | K72: x | L72: x | M72: Chute / trébuchement | N72: 01. Risques de chute de plain-pied (trébuchement, heurt ou autre perturbation de mouvement) | O72: Etat des sols | P72: normal | Q72: 5 | R72: 4 | S72: =Q72+R72 -> 9 | T72: 2 | U72: =VLOOKUP($T72,Cotation!$G$6:$H$10,2,(FALSE)) -> 5 | V72: =HLOOKUP($S72,Cotation!$I$5:$M$10,'Risk Register'!U72,(TRUE)) -> S | W72: Cheminements piétons stable et sans obstacle ou déformations du sol Signalisations au sol | X72: non | Y72: Chaussures de sécurité | Z72: 0.25 | AA72: Non | AB72: 0 | AC72: Respect des cheminement piéton / signaler les anomalies | AE72: =100%-(Z72+AB72+AD72) -> 0.75 | AF72: =S72*AE72 -> 6.75 | AG72: =HLOOKUP($AF72,Cotation!$I$5:$M$10,'Risk Register'!U72,(TRUE)) -> M
B73: Déplacement de plain-pied | C73: Déplacements de plain pied dans les locaux tertiaires | D73: x | E73: x | F73: x | G73: x | H73: x | I73: x | J73: x | K73: x | L73: x | M73: Chute / trébuchement | N73: 01. Risques de chute de plain-pied (trébuchement, heurt ou autre perturbation de mouvement) | O73: Etat des sols | P73: normal | Q73: 5 | R73: 3 | S73: =Q73+R73 -> 8 | T73: 2 | U73: =VLOOKUP($T73,Cotation!$G$6:$H$10,2,(FALSE)) -> 5 | V73: =HLOOKUP($S73,Cotation!$I$5:$M$10,'Risk Register'!U73,(TRUE)) -> S | W73: Cheminements piétons stable et sans obstacle ou déformations du sol | X73: non | Y73: Non applicable | Z73: 0.25 | AA73: Non | AB73: 0 | AC73: Respect des cheminement piéton / signaler les anomalies | AE73: =100%-(Z73+AB73+AD73) -> 0.75 | AF73: =S73*AE73 -> 6 | AG73: =HLOOKUP($AF73,Cotation!$I$5:$M$10,'Risk Register'!U73,(TRUE)) -> M
B74: Déplacement de plain-pied | C74: Déplacements de plain pied en extérieur (hors zone de coactivité) | D74: x | E74: x | F74: x | G74: x | H74: x | I74: x | J74: x | K74: x | L74: x | M74: Chute / trébuchement | N74: 01. Risques de chute de plain-pied (trébuchement, heurt ou autre perturbation de mouvement) | O74: Etat des sols | P74: normal | Q74: 5 | R74: 4 | S74: =Q74+R74 -> 9 | T74: 2 | U74: =VLOOKUP($T74,Cotation!$G$6:$H$10,2,(FALSE)) -> 5 | V74: =HLOOKUP($S74,Cotation!$I$5:$M$10,'Risk Register'!U74,(TRUE)) -> S | W74: Cheminements piétons stable et sans obstacle ou déformations du sol Signalisations au sol | X74: non | Y74: Chaussures de sécurité | Z74: 0.25 | AA74: Non | AB74: 0 | AC74: Respect des cheminement piéton / signaler les anomalies | AE74: =100%-(Z74+AB74+AD74) -> 0.75 | AF74: =S74*AE74 -> 6.75 | AG74: =HLOOKUP($AF74,Cotation!$I$5:$M$10,'Risk Register'!U74,(TRUE)) -> M
B75: Déplacement de plain-pied | C75: Utilisation des escaliers | D75: x | E75: x | F75: x | G75: x | H75: x | I75: x | J75: x | K75: x | L75: x | M75: Chute / trébuchement | N75: 01. Risques de chute de plain-pied (trébuchement, heurt ou autre perturbation de mouvement) | O75: Etat des marches | P75: Normal | Q75: 5 | R75: 3 | S75: =Q75+R75 -> 8 | T75: 3 | U75: =VLOOKUP($T75,Cotation!$G$6:$H$10,2,(FALSE)) -> 4 | V75: =HLOOKUP($S75,Cotation!$I$5:$M$10,'Risk Register'!U75,(TRUE)) -> S | W75: Conception des marches / nez de marches / rampes et rambarde | X75: non | Y75: Rambarde | Z75: 0.25 | AA75: Core safety training : elearning | AB75: 0 | AC75: Tenir la rampe / signaler les anomalies | AE75: =100%-(Z75+AB75+AD75) -> 0.75 | AF75: =S75*AE75 -> 6 | AG75: =HLOOKUP($AF75,Cotation!$I$5:$M$10,'Risk Register'!U75,(TRUE)) -> S
B76: Déplacement de plain-pied | C76: Déplacement en zone de coactivité Piétons / véhicule | F76: x | G76: x | H76: x | I76: x | J76: x | M76: Heurt / collision avec un véhicule | N76: 03. Risques liés aux circulations internes de véhicules | O76: Véhicules | P76: Normal | Q76: 5 | R76: 1 | S76: =Q76+R76 -> 6 | T76: 5 | U76: =VLOOKUP($T76,Cotation!$G$6:$H$10,2,(FALSE)) -> 2 | V76: =HLOOKUP($S76,Cotation!$I$5:$M$10,'Risk Register'!U76,(TRUE)) -> C | W76: Cheminements piétons stable et sans obstacle ou déformations du sol Signalisations au sol et signalisation verticales | X76: non | Y76: Chaussures de sécurité Gilet haute visibilité | Z76: 0.25 | AA76: Non | AB76: 0 | AC76: Plan de Prevention prise de connaissance du PDP Induction site Respect des cheminements piéton / signaler les anomalies Priorité aux véhicules | AD76: 0.25 | AE76: =100%-(Z76+AB76+AD76) -> 0.5 | AF76: =S76*AE76 -> 3 | AG76: =HLOOKUP($AF76,Cotation!$I$5:$M$10,'Risk Register'!U76,(TRUE)) -> S
B77: Travaux en hauteur | C77: Accès à uneplateforme camion | G77: x | H77: x | J77: x | K77: x | M77: Chute de hauteur / chute d'objet | N77: 02. Risques de chutes de hauteur | O77: Echelle | P77: Normal | Q77: 1 | R77: 1 | S77: =Q77+R77 -> 2 | T77: 3 | U77: =VLOOKUP($T77,Cotation!$G$6:$H$10,2,(FALSE)) -> 4 | V77: =HLOOKUP($S77,Cotation!$I$5:$M$10,'Risk Register'!U77,(TRUE)) -> M | W77: Equipement conforme et CE | X77: non | Y77: Casquette coquée Gants Lunettes de sécurité Chaussure de sécurité | Z77: 0.1 | AA77: non | AB77: 0 | AC77: Respect de la règle des 3 points de contact avec l'échelle Rester face à l'echelle vigilence en fonction des conditions météo | AD77: 0.1 | AE77: =100%-(Z77+AB77+AD77) -> 0.8 | AF77: =S77*AE77 -> 1.6 | AG77: =HLOOKUP($AF77,Cotation!$I$5:$M$10,'Risk Register'!U77,(TRUE)) -> F | AI77: Accident de travail fedex
B78: Travaux en hauteur | C78: Accès par échelle à crinoline | G78: x | H78: x | J78: x | K78: x | M78: Chute de hauteur / chute d'objet | N78: 02. Risques de chutes de hauteur | O78: Echelle à crinoline | P78: Normal | Q78: 1 | R78: 1 | S78: =Q78+R78 -> 2 | T78: 4 | U78: =VLOOKUP($T78,Cotation!$G$6:$H$10,2,(FALSE)) -> 3 | V78: =HLOOKUP($S78,Cotation!$I$5:$M$10,'Risk Register'!U78,(TRUE)) -> M | W78: Equipement conforme et CE | X78: Règle 1 - Autorisation de Travail ( compétence) Regle 5 - Travail en hauteur | Y78: casque avec jugulaire Gants Lunettes de sécurité Chaussure de sécurité Harnais disposition stop chute | Z78: 0.25 | AA78: Core safety training : elearning Formation PTW : Travaux en hauteur au dessus de 1,8 m Portdu Harnais | AB78: 0 | AC78: Analyse de risque avant travaux ou RAD Vérification de l'équipement avant utilisation (état de conservation, présence de l'ensemble des pièces, stabilité) Matériel ressencé et référencé Permis de travail en hauteur EA : verification des compétences | AD78: 0.25 | AE78: =100%-(Z78+AB78+AD78) -> 0.5 | AF78: =S78*AE78 -> 1 | AG78: =HLOOKUP($AF78,Cotation!$I$5:$M$10,'Risk Register'!U78,(TRUE)) -> M
B79: Traitement de l'eau | C79: Vérifier le niveau de produit de traitement. | G79: x | H79: x | J79: x | M79: Projection de produits chimiques / Inhalation de vapeurs chimiques / brûlure | N79: 07. Risques liés aux produits chimiques, aux émissions et aux déchets | O79: Circuit injection réactif | P79: Normal | Q79: 3 | R79: 2 | S79: =Q79+R79 -> 5 | T79: 1 | U79: =VLOOKUP($T79,Cotation!$G$6:$H$10,2,(FALSE)) -> 6 | V79: =HLOOKUP($S79,Cotation!$I$5:$M$10,'Risk Register'!U79,(TRUE)) -> F | W79: Cuves de réactif fermées Etiquettage des cuves avec mention de danger | X79: non | Y79: Vêtement de travail couvrant Gants de protection chimique vérifier les EPI recommandés de la FDS au préalable Rubrique 8 Lunette de sécurité. | Z79: 0.25 | AA79: non | AB79: 0 | AC79: FDS des produits utilisés Procedure substance dangeureuse COSH Alayse de risque produit chimique Seirich Respect strict des consignes de tri Produits sur rétention | AD79: 0.25 | AE79: 0.5 | AF79: 2.5 | AG79: =HLOOKUP($AF79,Cotation!$I$5:$M$10,'Risk Register'!U79,(TRUE)) -> F
B80: Traitement de l'eau | C80: Contrôler les consommations de produit de traitement | G80: x | H80: x | J80: x | M80: Contrôle visuel uniquement | N80: 07. Risques liés aux produits chimiques, aux émissions et aux déchets | O80: Circuit injection réactif | P80: Normal | Q80: 3 | R80: 1 | S80: =Q80+R80 -> 4 | T80: 1 | U80: =VLOOKUP($T80,Cotation!$G$6:$H$10,2,(FALSE)) -> 6 | V80: =HLOOKUP($S80,Cotation!$I$5:$M$10,'Risk Register'!U80,(TRUE)) -> F | W80: Cuves de réactif fermées Etiquettage des cuves avec mention de danger | X80: non | Y80: Vêtement de travail couvrant Gants de protection chimique vérifier les EPI recommandés de la FDS au préalable Rubrique 8 Lunette de sécurité. | Z80: 0.25 | AA80: non | AB80: 0 | AC80: FDS des produits utilisés Procedure substance dangeureuse COSH Alayse de risque produit chimique Seirich Respect strict des consignes de tri Produits sur rétention | AD80: 0.25 | AE80: 0.5 | AF80: 2 | AG80: =HLOOKUP($AF80,Cotation!$I$5:$M$10,'Risk Register'!U80,(TRUE)) -> F
B81: Traitement de l'eau | C81: Contrôle le fonctionnement des pompes d’injection de produits | G81: x | H81: x | J81: x | M81: Projection de produits chimiques / Inhalation de vapeurs chimiques / brûlure | N81: 07. Risques liés aux produits chimiques, aux émissions et aux déchets | O81: Circuit injection réactif | P81: Normal | Q81: 4 | R81: 3 | S81: =Q81+R81 -> 7 | T81: 3 | U81: =VLOOKUP($T81,Cotation!$G$6:$H$10,2,(FALSE)) -> 4 | V81: =HLOOKUP($S81,Cotation!$I$5:$M$10,'Risk Register'!U81,(TRUE)) -> S | W81: Favoriser la mise en place de protection physique sur les pompes et doubles enveloppe sur les circuits d'injection | X81: non | Y81: Vêtement de travail couvrant Gants de protection chimique vérifier les EPI recommandés de la FDS au préalable Rubrique 8 Lunette de sécurité. | Z81: 0.25 | AA81: non | AB81: 0 | AC81: FDS des produits utilisés Procedure substance dangeureuse COSH Alayse de risque produit chimique Seirich Respect strict des consignes de tri Produits sur rétention | AD81: 0.25 | AE81: 0.5 | AF81: 3.5 | AG81: =HLOOKUP($AF81,Cotation!$I$5:$M$10,'Risk Register'!U81,(TRUE)) -> M
B82: Traitement de l'eau | C82: Contrôler le déclenchement des approvisionnements | G82: x | H82: x | M82: Pas de risque identifié pour cette tâche | N82: 07. Risques liés aux produits chimiques, aux émissions et aux déchets | O82: Circuit injection réactif | P82: Normal | Q82: 3 | R82: 1 | S82: =Q82+R82 -> 4 | T82: 1 | U82: =VLOOKUP($T82,Cotation!$G$6:$H$10,2,(FALSE)) -> 6 | V82: =HLOOKUP($S82,Cotation!$I$5:$M$10,'Risk Register'!U82,(TRUE)) -> F | W82: Non applicable | X82: non | Y82: Vêtement de travail couvrant Gants de protection chimique vérifier les EPI recommandés de la FDS au préalable Rubrique 8 Lunette de sécurité. | Z82: 0.25 | AA82: Non applicable | AB82: 0 | AC82: FDS des produits utilisés Procedure substance dangeureuse COSH Alayse de risque produit chimique Seirich | AE82: 1 | AF82: 4 | AG82: =HLOOKUP($AF82,Cotation!$I$5:$M$10,'Risk Register'!U82,(TRUE)) -> F
B83: Traitement de l'eau | C83: Nettoyer les bacs, tuyaux et cannes d’injection | G83: x | H83: x | J83: x | M83: Risques de projections chimiques / Inhalation / Brûlure | N83: 07. Risques liés aux produits chimiques, aux émissions et aux déchets | O83: Circuit injection réactif | P83: Normal | Q83: 1 | R83: 3 | S83: =Q83+R83 -> 4 | T83: 3 | U83: =VLOOKUP($T83,Cotation!$G$6:$H$10,2,(FALSE)) -> 4 | V83: =HLOOKUP($S83,Cotation!$I$5:$M$10,'Risk Register'!U83,(TRUE)) -> M | W83: Etiquetage des cuves avec mention de danger | X83: non | Y83: Vêtement de travail couvrant Gants de protection chimique vérifier les EPI recommandés de la FDS au préalable Rubrique 8 Lunette de sécurité. | Z83: 0.25 | AA83: Formation aux risques chimiques | AB83: 0.1 | AC83: Consignation électrique préalable des pompes doseuses - Détenir et avoir lu la FDS des produits avant opération Procedure substance dangeureuse COSH Alayse de risque produit chimique Seirich Les rejets sont récupérés dans des bidons identifiés Les chiffons souillées sont considérés comme des DIS | AD83: 0.1 | AE83: 0.55 | AF83: 2.2 | AG83: =HLOOKUP($AF83,Cotation!$I$5:$M$10,'Risk Register'!U83,(TRUE)) -> M
B84: Traitement de l'eau | C84: Suivi du Titre Hydrométrique | G84: x | H84: x | J84: x | M84: Pas de risque identifié pour cette tâche | N84: 07. Risques liés aux produits chimiques, aux émissions et aux déchets | O84: Adoucisseur | P84: Normal | Q84: 4 | R84: 1 | S84: =Q84+R84 -> 5 | T84: 1 | U84: =VLOOKUP($T84,Cotation!$G$6:$H$10,2,(FALSE)) -> 6 | V84: =HLOOKUP($S84,Cotation!$I$5:$M$10,'Risk Register'!U84,(TRUE)) -> F | W84: Non applicable | X84: non | Y84: Non applicable | Z84: 0.25 | AA84: Non applicable | AB84: 0 | AC84: Suivi en continu | AD84: 0.1 | AE84: 1 | AF84: 5 | AG84: =HLOOKUP($AF84,Cotation!$I$5:$M$10,'Risk Register'!U84,(TRUE)) -> F
B85: Traitement de l'eau | C85: Rajout de sels | G85: x | H85: x | J85: x | M85: port de charge (Sac de sel 25KG) + risque de coupure à l'ouverture des sacs | N85: 05. Risques liés à la manutention manuelle de charge | O85: Adoucisseur | P85: Normal | Q85: 4 | R85: 3 | S85: =Q85+R85 -> 7 | T85: 2 | U85: =VLOOKUP($T85,Cotation!$G$6:$H$10,2,(FALSE)) -> 5 | V85: =HLOOKUP($S85,Cotation!$I$5:$M$10,'Risk Register'!U85,(TRUE)) -> M | W85: Non applicable | X85: non | Y85: Chariot Vêtement de travail couvrant Gants anticoupure vérifier les EPI recommandés de la FDS au préalable Rubrique 8 Lunette de sécurité. | Z85: 0.25 | AA85: Coresafety training : manutention manuellle | AB85: 0 | AC85: Utilisation d'un chariot pour le transort des sacs. Cutter interdit - utiliser un outil à lame rétractable pour l'ouverture des sacs | AD85: 0.25 | AE85: 0.75 | AF85: 5.25 | AG85: =HLOOKUP($AF85,Cotation!$I$5:$M$10,'Risk Register'!U85,(TRUE)) -> M
B86: Traitement de l'eau | C86: Nettoyage et désinfection du bac à sel | G86: x | H86: x | J86: x | M86: Chute / glissade | N86: 01. Risques de chute de plain-pied (trébuchement, heurt ou autre perturbation de mouvement) | O86: Adoucisseur | P86: Normal | Q86: 4 | R86: 3 | S86: =Q86+R86 -> 7 | T86: 3 | U86: =VLOOKUP($T86,Cotation!$G$6:$H$10,2,(FALSE)) -> 4 | V86: =HLOOKUP($S86,Cotation!$I$5:$M$10,'Risk Register'!U86,(TRUE)) -> S | W86: Non applicable | X86: non | Y86: Chaussures de sécurité SRC3c/ vêtement de travail/ casquette de sécurité | Z86: 0.25 | AE86: 0.75 | AF86: 5.25 | AG86: =HLOOKUP($AF86,Cotation!$I$5:$M$10,'Risk Register'!U86,(TRUE)) -> M
B87: Traitement de l'eau | C87: Nettoyage et désinfection du bac à sel | G87: x | H87: x | J87: x | M87: Risque de projection d'eau | N87: 07. Risques liés aux produits chimiques, aux émissions et aux déchets | O87: Adoucisseur | P87: Normal | Q87: 1 | R87: 2 | S87: =Q87+R87 -> 3 | T87: 2 | U87: =VLOOKUP($T87,Cotation!$G$6:$H$10,2,(FALSE)) -> 5 | V87: =HLOOKUP($S87,Cotation!$I$5:$M$10,'Risk Register'!U87,(TRUE)) -> F | W87: Non applicable | X87: non | Y87: Vêtement de travail couvrant Gants anticoupure vérifier les EPI recommandés de la FDS au préalable Rubrique 8 Lunette de sécurité. | Z87: 0.25 | AA87: Non applicable | AB87: 0 | AC87: FDS des produits utilisés Procedure substance dangeureuse COSH Alayse de risque produit chimique Seirich | AE87: 1 | AF87: 3 | AG87: =HLOOKUP($AF87,Cotation!$I$5:$M$10,'Risk Register'!U87,(TRUE)) -> F
B88: Traitement de l'eau | C88: Vérifier intégrité des disconnecteurs / recherche de fuite | G88: x | H88: x | J88: x | M88: Heurt / choc | N88: 05. Risques liés à la manutention manuelle de charge | O88: Disconnecteur sur eau d’appoint | P88: Normal | Q88: 1 | R88: 1 | S88: =Q88+R88 -> 2 | T88: 2 | U88: =VLOOKUP($T88,Cotation!$G$6:$H$10,2,(FALSE)) -> 5 | V88: =HLOOKUP($S88,Cotation!$I$5:$M$10,'Risk Register'!U88,(TRUE)) -> F | W88: Raccordement dans les règles de l'art - tuyauterie d'évacuation des l'eau | X88: non | Y88: Chaussures de sécurité SRC3c/ vêtement de travail/ casquette de sécurité | Z88: 0.25 | AA88: Non applicable | AB88: 0 | AC88: Non applicable | AD88: 0 | AE88: 1 | AF88: 1 | AG88: =HLOOKUP($AF88,Cotation!$I$5:$M$10,'Risk Register'!U88,(TRUE)) -> F
B89: Vannes, vanne motorisée, électrovannes, clapets anti-retour, pompe de recirculation | C89: Vérifier l’état général (usure, tartre, corrosion...) et le bon fonctionnement | G89: x | H89: x | J89: x | M89: TMS / heurt / choc / ecrasement | N89: 05. Risques liés à la manutention manuelle de charge | O89: Vannes, vanne motorisée, électrovannes, clapets anti-retour… | P89: Normal | Q89: 1 | R89: 1 | S89: =Q89+R89 -> 2 | T89: 2 | U89: =VLOOKUP($T89,Cotation!$G$6:$H$10,2,(FALSE)) -> 5 | V89: =HLOOKUP($S89,Cotation!$I$5:$M$10,'Risk Register'!U89,(TRUE)) -> F | W89: Raccordement dans les règles de l'art - tuyauterie d'évacuation des l'eau | X89: non | Y89: Chaussures de sécurité SRC3c/ vêtement de travail/ casquette de sécurité | Z89: 0.25 | AA89: Non applicable | AB89: 0 | AC89: Non applicable | AD89: 0 | AE89: 1 | AF89: 1 | AG89: =HLOOKUP($AF89,Cotation!$I$5:$M$10,'Risk Register'!U89,(TRUE)) -> F
B90: Réseau d'eau | C90: Purger les réseaux, y compris points bas | G90: x | H90: x | J90: x | M90: Pression / glissade / chute de plain pied | N90: 01. Risques de chute de plain-pied (trébuchement, heurt ou autre perturbation de mouvement) | O90: Réseau | P90: Normal | Q90: 1 | R90: 1 | S90: =Q90+R90 -> 2 | T90: 2 | U90: =VLOOKUP($T90,Cotation!$G$6:$H$10,2,(FALSE)) -> 5 | V90: =HLOOKUP($S90,Cotation!$I$5:$M$10,'Risk Register'!U90,(TRUE)) -> F | W90: Raccordement dans les règles de l'art - tuyauterie d'évacuation des l'eau | X90: non | Y90: Chaussures de sécurité SRC3c/ vêtement de travail/ casquette de sécurité | Z90: 0.25 | AA90: Non applicable | AB90: 0 | AC90: Non applicable | AD90: 0 | AE90: 1 | AF90: 1 | AG90: =HLOOKUP($AF90,Cotation!$I$5:$M$10,'Risk Register'!U90,(TRUE)) -> F
B91: Travaux en hauteur | C91: Travail sur toiture | G91: x | H91: x | J91: x | M91: Chute de hauteur / chute d'objet | N91: 02. Risques de chutes de hauteur | O91: Toiture | P91: Normal | Q91: 3 | R91: 2 | S91: =Q91+R91 -> 5 | T91: 4 | U91: =VLOOKUP($T91,Cotation!$G$6:$H$10,2,(FALSE)) -> 3 | V91: =HLOOKUP($S91,Cotation!$I$5:$M$10,'Risk Register'!U91,(TRUE)) -> S | W91: Gardes-corps Présence de points d'ancrage ou d'une ligne de vie | X91: Règle 1 - Autorisation de Travail ( compétence) Regle 5 - Travail en hauteur | Y91: Casque / Chaussure de sécurité / gants de travail / Lunettes de sécurité Port du harnais en cas d'absence de grade corps et à proximité des skydome non muni de barreaux anti-chute | Z91: 0.25 | AA91: Si absence de garde-corps - formation au port du harnais et travaux en hauteur | AB91: 0.25 | AC91: Analyse de risque avant travaux ou RAD Vérification de l'équipement avant utilisation (état de conservation, présence de l'ensemble des pièces, stabilité) Verification annuele reglementaire des harnais longes et mousquetons Matériel ressencé et référencé Permis de travail en hauteur EA : verification des compétences | AD91: 0.25 | AE91: =100%-(Z91+AB91+AD91) -> 0.25 | AF91: =S91*AE91 -> 1.25 | AG91: =HLOOKUP($AF91,Cotation!$I$5:$M$10,'Risk Register'!U91,(TRUE)) -> M
B92: Tout travail | C92: Travail sous pression | D92: x | E92: x | F92: x | G92: x | H92: x | I92: x | J92: x | K92: x | L92: x | M92: Risques psychsociaux | N92: 17. Risques Psychosociaux | O92: Tout équipement | P92: Normal | Q92: 4 | R92: 4 | S92: =Q92+R92 -> 8 | T92: 3 | U92: =VLOOKUP($T92,Cotation!$G$6:$H$10,2,(FALSE)) -> 4 | V92: =HLOOKUP($S92,Cotation!$I$5:$M$10,'Risk Register'!U92,(TRUE)) -> S | W92: Non applicable | X92: Non | Y92: Non applicable | Z92: 0 | AA92: Formation des managers à l'identification des salariés en détresse psychologique | AB92: 0 | AC92: Moka Care - soutien psychologique Droit à la déconnexion | AD92: 0.25 | AE92: =100%-(Z92+AB92+AD92) -> 0.75 | AF92: =S92*AE92 -> 6 | AG92: =HLOOKUP($AF92,Cotation!$I$5:$M$10,'Risk Register'!U92,(TRUE)) -> S | AH92: Engager des mesures concrète d'organisation du travail, de formation des salariés et de communication interne
B93: Tout travail | C93: - Conflits - Isolement - Pression de la hiérarchie - Objectifs professionnels non smart - Harcèlement - Surcharge d'heures de travail | D93: x | E93: x | F93: x | G93: x | H93: x | I93: x | J93: x | K93: x | L93: x | M93: Traumatismes physique et /ou psychique, dépression, Burn out, pathologie aigue ou chroniques lié au stress, troubles psychosomatique, risque de suicide | N93: 17. Risques Psychosociaux | O93: Tout équipement | P93: Normal | Q93: 4 | R93: 4 | S93: =Q93+R93 -> 8 | T93: 3 | U93: =VLOOKUP($T93,Cotation!$G$6:$H$10,2,(FALSE)) -> 4 | V93: =HLOOKUP($S93,Cotation!$I$5:$M$10,'Risk Register'!U93,(TRUE)) -> S | W93: Non applicable | X93: Non | Y93: Non applicable | Z93: 0 | AA93: Formation des managers à l'identification des salariés en détresse psychologique | AB93: 0 | AC93: Moka Care - soutien psychologique Droit à la déconnexion | AD93: 0.25 | AE93: =100%-(Z93+AB93+AD93) -> 0.75 | AF93: =S93*AE93 -> 6 | AG93: =HLOOKUP($AF93,Cotation!$I$5:$M$10,'Risk Register'!U93,(TRUE)) -> S | AH93: Engager des mesures concrète d'organisation du travail, de formation des salariés et de communication interne
B94: Déplacement d'astreinte / Travail de nuit occasionnel | C94: Tavail isolé | F94: x | G94: x | H94: x | L94: x | M94: RPS Fatigue et Troubles du sommeil Accident de la route | N94: 20. Risques liés aux rythmes de travail spécifiques (travail de nuit, équipe successive, etc.) | O94: Tout équipement | P94: dégradé | Q94: 2 | R94: 2 | S94: =Q94+R94 -> 4 | T94: 4 | U94: =VLOOKUP($T94,Cotation!$G$6:$H$10,2,(FALSE)) -> 3 | V94: =HLOOKUP($S94,Cotation!$I$5:$M$10,'Risk Register'!U94,(TRUE)) -> S | W94: Non applicable | X94: Non | Y94: Non applicable | Z94: 0 | AA94: Non applicable | AB94: 0 | AC94: Intervention interdite sur les sites ne disposant pas de gardiennage. Astreinte non doublée car le nombre de sortie ne le justifie pas. Contrôle chaque matin par le cadre d'astreinte pour surveiller le respect des temps de repos, debrief des opérations et des rapports, etc. | AD94: 0.25 | AE94: =100%-(Z94+AB94+AD94) -> 0.75 | AF94: =S94*AE94 -> 3 | AG94: =HLOOKUP($AF94,Cotation!$I$5:$M$10,'Risk Register'!U94,(TRUE)) -> M | AH94: Rédaction et diffuson d'une note interne rappelant les règles et obligations
B95: Déplacement zone peu fréquenté, sans visuel | C95: Tavail isolé | F95: x | G95: x | H95: x | I95: x | J95: x | K95: x | M95: Ralentissement des secours | N95: 20. Risques liés aux rythmes de travail spécifiques (travail de nuit, équipe successive, etc.) | O95: NA | P95: dégradé | Q95: 2 | R95: 2 | S95: =Q95+R95 -> 4 | T95: 5 | U95: =VLOOKUP($T95,Cotation!$G$6:$H$10,2,(FALSE)) -> 2 | V95: =HLOOKUP($S95,Cotation!$I$5:$M$10,'Risk Register'!U95,(TRUE)) -> S | W95: Non applicable | X95: Non | Y95: Possibilité de mise à disposition de DATI ( application mobile sur smartphone) | Z95: 0.25 | AB95: 0 | AC95: Organisation du travail :constitution d’équipes ou de binômes Moyens de communication: dispositifs d’alarme (DATI) Surveillance :des passages périodiques d’une autre personne information : Former les travailleurs isolés sur les risques spécifiques à leur poste et les procédures à suivre en cas d’urgence | AD95: 0.1 | AE95: =100%-(Z95+AB95+AD95) -> 0.65 | AG95: =HLOOKUP($AF95,Cotation!$I$5:$M$10,'Risk Register'!U95,(TRUE)) -> M
B96: Travail de nuit habituel ou équipe successive | C96: Travail isolé | D96: x | E96: x | F96: x | G96: x | H96: x | I96: x | J96: x | K96: x | L96: x | M96: RPS Fatigue et Troubles du sommeil Accident de la route | N96: 20. Risques liés aux rythmes de travail spécifiques (travail de nuit, équipe successive, etc.) | O96: Tout équipement | P96: dégradé | Q96: 2 | R96: 2 | S96: =Q96+R96 -> 4 | T96: 4 | U96: =VLOOKUP($T96,Cotation!$G$6:$H$10,2,(FALSE)) -> 3 | V96: =HLOOKUP($S96,Cotation!$I$5:$M$10,'Risk Register'!U96,(TRUE)) -> S | W96: Non applicable | X96: Non | Y96: Non applicable | Z96: 0 | AA96: Non applicable | AB96: 0 | AC96: Surveillance médicale renforcée Aménagement du temps de travail pour limiter le nombre de nuits réalisées | AD96: 0.25 | AE96: =100%-(Z96+AB96+AD96) -> 0.75 | AF96: =S96*AE96 -> 3 | AG96: =HLOOKUP($AF96,Cotation!$I$5:$M$10,'Risk Register'!U96,(TRUE)) -> M
B97: Télétravail | C97: Travail isolé | D97: x | E97: x | F97: x | G97: x | H97: x | I97: x | J97: x | K97: x | L97: x | M97: Isolement social et professionnel : Sentiment d'abandon et perte de lien avec l'équipe. Déséquilibre vie pro/perso : Difficulté à déconnecter, allongement du temps de travail, empiètement du travail sur la vie familiale. Surcharge et stress : Objectifs flous ou inatteignables, management abusif ou contrôle excessif à distance. Épuisement professionnel (Burn-out) : Risque accru lié à la difficulté de s'imposer des pauses. | N97: 17. Risques Psychosociaux | O97: Tout équipement | P97: Normal | Q97: 3 | R97: 2 | S97: =Q97+R97 -> 5 | T97: 3 | U97: =VLOOKUP($T97,Cotation!$G$6:$H$10,2,(FALSE)) -> 4 | V97: =HLOOKUP($S97,Cotation!$I$5:$M$10,'Risk Register'!U97,(TRUE)) -> M | W97: Non applicable | X97: Non | Y97: Aménagement : Fournir un matériel ergonomique (écran, chaise, clavier) et s'assurer de l'adéquation du lieu de travail. | Z97: 0 | AA97: Formation : Former les salariés et les managers aux outils numériques et à la gestion du travail à distance. | AB97: 0 | AC97: Organisation : Mettre en place un droit à la déconnexion effectif, définir des plages horaires de joignabilité et organiser des réunions régulières pour maintenir le lien. Management : Adapter le suivi en se concentrant sur les résultats plutôt que sur le temps de connexion. Réaliser des entretiens annuels dédiés aux conditions de télétravail. Routine : Pour le salarié, maintenir une routine (horaires fixes, pauses, se préparer) pour bien scinder vie pro et vie perso. | AD97: 0.1 | AE97: =100%-(Z97+AB97+AD97) -> 0.9 | AF97: =S97*AE97 -> 4.5 | AG97: =HLOOKUP($AF97,Cotation!$I$5:$M$10,'Risk Register'!U97,(TRUE)) -> M
B98: Conduite de véhicule | C98: Circulation en 2 roue | D98: x | E98: x | F98: x | G98: x | H98: x | I98: x | J98: x | K98: x | L98: x | M98: Accident de la route | N98: 04. Risques routiers en mission | O98: 2 roues | P98: Normal | Q98: 5 | R98: 4 | T98: 5 | V98: =HLOOKUP($S97,Cotation!$I$5:$M$10,'Risk Register'!U97,(TRUE)) -> M | W98: Sécurité intrinsinque des VL | X98: Règle 4 - Conduite | Y98: Dotation d'EPI spécialement conçus pour les 2 roues (casque, gants, blouson, bottes) | Z98: 0.25 | AA98: Formation aux risques routiers | AB98: 0 | AC98: Code de la route applicable à tous Charte de conduite de vehicule CBRE Maintenance des véhicules CBRE - Contrat de "full maintenance" intégré - Contrat intégrant pneumatiques été/hiver | AD98: 0.25 | AE98: =100%-(Z98+AB98+AD98) -> 0.5 | AG98: =HLOOKUP($AF97,Cotation!$I$5:$M$10,'Risk Register'!U97,(TRUE)) -> M | AH98: Procédure de vérification (checklist) des véhicules à réaliser par les managers à remettreen place
B99: Exposition aux risques biologiques | C99: Exposition à la légionnelle Eau Chaude sanitaire (Maintenance) | H99: x | I99: x | J99: x | M99: Maladie professionnelle / légionnelose | N99: 08. Risques liés aux agents biologiques | O99: ECS | P99: Normal | Q99: 1 | R99: 1 | S99: =Q99+R99 -> 2 | T99: 3 | U99: =VLOOKUP($T99,Cotation!$G$6:$H$10,2,(FALSE)) -> 4 | V99: =HLOOKUP($S99,Cotation!$I$5:$M$10,'Risk Register'!U99,(TRUE)) -> M | X99: Règle 1 - Autorisation de Travail ( compétence) | Y99: Masque FFP3 Casquette coquée Chaussure de sécurité Gants Lunettes de sécurité | Z99: 0.25 | AA99: Formation aux risques légionnelles Formation Talent Coach legionelle Formation The Academy eau et legionelle | AB99: 0.25 | AC99: Logbook Water & Legionella afin de maîtriser le risque pour les utilisateurs. Sensibiliser à consultez rapidement un médecin en cas de signes évocateurs de la maladie (pneumonie sévère, toux sèche, maux de tête, fièvre élevée, fatigue, etc.) Respect de la procedure CBRE Hygiène de l'eau pour prevenir et surveiller la présence de legionelle dans les réseaux. Mise en place du Carnet Sanitaire | AD99: 0.25 | AE99: =100%-(Z99+AB99+AD99) -> 0.25 | AF99: =S99*AE99 -> 0.5 | AG99: =HLOOKUP($AF99,Cotation!$I$5:$M$10,'Risk Register'!U99,(TRUE)) -> F
B100: Exposition aux risques biologiques | C100: Exposition à la légionnelle operation des Tours | H100: x | I100: x | J100: x | M100: Maladie professionnelle / légionnelose | N100: 08. Risques liés aux agents biologiques | O100: Tour Aéroréfrigérante | P100: Normal | Q100: 1 | R100: 1 | S100: =Q100+R100 -> 2 | T100: 3 | U100: =VLOOKUP($T100,Cotation!$G$6:$H$10,2,(FALSE)) -> 4 | V100: =HLOOKUP($S100,Cotation!$I$5:$M$10,'Risk Register'!U100,(TRUE)) -> M | X100: Règle 1 - Autorisation de Travail ( compétence) | Y100: Masque FFP3 Casquette coquée Chaussure de sécurité Gants Lunettes de sécurité | Z100: 0.25 | AA100: Formation aux risques légionnelles Formation Talent Coach legionelle Formation The Academy eau et legionelle Coorditateur : formation (réglementaire) pour les responsables du management de la légionelle des Tours Aéroréfrigérente, ainsi qu'aux procedure CBRE Hygiène de l'eau pour prevenir et surveiller la présence de legionelle | AB100: 0.25 | AC100: Logbook Water & Legionella afin de maîtriser le risque pour les utilisateurs. Sensibiliser à consultez rapidement un médecin en cas de signes évocateurs de la maladie (pneumonie sévère, toux sèche, maux de tête, fièvre élevée, fatigue, etc.) Respect de la procedure CBRE Hygiène de l'eau pour prevenir et surveiller la présence de legionelle dans les réseaux. Mise en place du Carnet Sanitaire | AD100: 0.25 | AE100: =100%-(Z100+AB100+AD100) -> 0.25 | AF100: =S100*AE100 -> 0.5 | AG100: =HLOOKUP($AF100,Cotation!$I$5:$M$10,'Risk Register'!U100,(TRUE)) -> F
B101: Exposition aux risques electrique | C101: Court circuit | D101: x | E101: x | F101: x | M101: electrisation | N101: 14. Risques liés à l'électricité | O101: equipements electriques defectueux | P101: dégradé | Q101: 1 | R101: 1 | S101: =Q101+R101 -> 2 | T101: 3 | U101: =VLOOKUP($T101,Cotation!$G$6:$H$10,2,(FALSE)) -> 4 | V101: =HLOOKUP($S101,Cotation!$I$5:$M$10,'Risk Register'!U101,(TRUE)) -> M | W101: tableau electrique fermé | X101: Règle 1 - Autorisation de Travail ( compétence) | Y101: tableau electrique fermé | Z101: 0.25 | AA101: Core safety training : l'electricité | AB101: 0.25 | AC101: Procedure WKEQ | AD101: 0.1 | AE101: =100%-(Z101+AB101+AD101) -> 0.4 | AF101: =S101*AE101 -> 0.8 | AG101: =HLOOKUP($AF101,Cotation!$I$5:$M$10,'Risk Register'!U101,(TRUE)) -> F

Sheet Cotation
B2: Fréquence d'exposition au danger
B3: 1 | C3: Jamais à rarement | D3: Jamais exposé à 1 fois par an | F3: GRAVITE (G) | I3: Fréquence + probabilité
B4: 2 | C4: Quelque fois | D4: Exposé 1 fois par mois | I4: <2 | J4: 2<Class<4 | K4: 4<Class<6 | L4: 6<Class<8 | M4: 8<Class<10
B5: 3 | C5: De temps en temps | D5: Exposé 1 fois par semaine | H5: 1 | I5: 0 | J5: 2 | K5: 4 | L5: 6 | M5: 8
B6: 4 | C6: Régulièrement | D6: Exposé 1 fois par jour | F6: Catastrophique | G6: 5 | H6: 2 | I6: M | J6: S | K6: S | L6: C | M6: C
B7: 5 | C7: En continue | D7: Exposé plusieurs fois par jour | F7: Critique | G7: 4 | H7: 3 | I7: M | J7: M | K7: S | L7: S | M7: C
F8: Sérieuse ou Sévère | G8: 3 | H8: 4 | I8: F | J8: M | K8: M | L8: S | M8: S
B9: Probabilité d'occurrence d'un accident | F9: Conséquente | G9: 2 | H9: 5 | I9: F | J9: F | K9: M | L9: M | M9: S
B10: 1 | C10: Impossible à improbable | D10: Jamais rencontré | F10: Mineur | G10: 1 | H10: 6 | I10: F | J10: F | K10: F | L10: M | M10: M
B11: 2 | C11: Très peu probable | D11: Vu une fois
B12: 3 | C12: Peu probable | D12: Survenance dans l'année
B13: 4 | C13: Probable | D13: Survenance dans le mois
B14: 5 | C14: Très probable à certain | D14: Très fréquent à systématique
B16: Echelle de Gravité
B17: 1 | C17: Mineure | D17: Accident bénin / premiers soins
B18: 2 | C18: Modérée | D18: Lésion réversible nécessitant des soins hors hospitalisation
B19: 3 | C19: Significative | D19: Lésion réversible nécessitant une hospitalisation / Maladie proffesionnelle réversible / handicap temporaire
B20: 4 | C20: Critique | D20: Victime unique : Décès / Lésions irréversibles / Handicap permanent / Maladie professionnelle irréversible
B21: 5 | C21: Catastrophique | D21: Victimes multiples : Décès / Lésions irréversibles / Handicap permanent / Maladie professionnelle irréversible
B25: Equipement de protection
B26: 0 | C26: Pas d'équipement de protection, ni individuelle, ni collectif
B27: 0.1 | C27: Equipement de protection individuel adapté, porté et vérifié
B28: 0.25 | C28: Equipement de protection collectif installé, adapté et maintenu
B30: Formation
B31: 0 | C31: Aucune formation
B32: 0.1 | C32: Formation et sensibilisation réglementaire
B33: 0.25 | C33: Formation et sensibilisation complémentaire
B35: Mesures organisationnelles
B36: 0 | C36: Aucune
B37: 0.1 | C37: Présence de procédures et d'affichage
B38: 0.25 | C38: Connaissance et respect des procédures et des affichages
